Workbook
Name p: 'Cost Summary'!$B$21
Name Costing_Sheet_Multiple_Location.2023.xlsx: 'Cost Summary'!$B$21
Name Costing_Sheet_Multiple_Location.2023.xlsx: 'Cost Summary'!$B$21
Name Costing_Sheet_Multiple_Location.2023.xlsx: 'Cost Summary'!$B$21
Name Costing_Sheet_Multiple_Location.2023.xlsx: 'Cost Summary'!$B$21
Name Costing_Sheet_Multiple_Location.2023.xlsx: 'Cost Summary'!$B$21
Name Costing_Sheet_Multiple_Location.2023.xlsx: 'Cost Summary'!$B$21
Name Costing_Sheet_Multiple_Location.2023.xlsx: 'Cost Summary'!$B$21

Sheet Cost Summary
A1: Customer and Project Scope -
A3: AINSWORTH LABOUR
A4: Item | B4: Task | C4: # of techs | D4: Days | E4: Hours | F4: Total Hours | G4: COST | H4: Subtotal 1 | I4: Margin | J4: Subtotal 2
A5: Project Management
A6: 1 | B6: Engineering/Meetings | C6: 0 | D6: 0 | F6: =C6*D6*E6 | G6: 90 | H6: =F6*G6 | I6: 0.85 | J6: =H6/I6
A7: 2 | B7: Project Management | C7: 0.05 | D7: 1 | E7: 1 | F7: =C7*D7*E7 | G7: =J6+J8+J9+J10+J11+J12+J16+J27+J32 | H7: =F7*G7 | I7: 0.85 | J7: =H7/I7
A8: 3 | B8: ESA Submissions | F8: =C8*D8*E8 | G8: 2000 | H8: =F8*G8 | I8: 0.85 | J8: =H8/I8
A9: 4 | B9: Misc. Subcontractors | C9: 0.05 | D9: 1 | E9: 1 | F9: =C9*D9*E9 | G9: ='Location 1'!P37+'Location 2'!P33+'Location 3'!P36+'Location 4'!P36+'Location 5'!P36+'Location 6'!P36+'Option 1'!P36 | H9: =F9*G9 | I9: 0.85 | J9: =H9/I9
A10: 5 | B10: Misc. Materials | C10: 0.05 | D10: 1 | E10: 1 | F10: =C10*D10*E10 | G10: ='Location 1'!P42+'Location 2'!P44+'Location 3'!P62+'Location 4'!P62+'Location 5'!P62+'Location 6'!P62+'Option 1'!P62 | H10: =F10*G10 | I10: 0.85 | J10: =H10/I10
A11: 6 | B11: Health and Safety | F11: =C11*D11*E11 | G11: 80 | H11: =F11*G11 | I11: 0.85 | J11: =H11/I11
A12: 7 | B12: Lodging | F12: =C12*D12*E12 | H12: =F12*G12 | I12: 0.85 | J12: =H12/I12
A13: Total Management | F13: =SUM(F6:F12) | H13: =SUM(H6:H12) | J13: =SUM(J6:J12)
A15: Labour
A16: 1 | B16: Other | F16: =C16*D16*E16 | H16: =F16*G16 | I16: 0.85 | J16: =H16/I16
A17: Sub Total Labour | F17: =SUM(F16:F16) | H17: =SUM(H16:H16) | J17: =SUM(J16:J16)
A18: Subtotal Labour | F18: =F13+F17 | H18: =H13+H17 | J18: =J13+J17
A19: Sheet Cost Summary
A20: Item | B20: Task | C20: Surcharge | D20: Days/Units | E20: Other | F20: Total Surcharge | G20: Unit Price | H20: Subtotal 1 | I20: Margin | J20: Subtotal 2
A21: 1 | B21: ='Location 1'!R1 | C21: 1 | D21: 1 | E21: 1 | F21: =C21*D21*E21 | G21: ='Location 1'!P53 | H21: =(F21*G21) | I21: 1 | J21: =H21/I21
A22: 2 | B22: ='Location 2'!R1 | C22: 1 | D22: 1 | E22: 1 | F22: =C22*D22*E22 | G22: ='Location 2'!P55 | H22: =(F22*G22) | I22: 1 | J22: =H22/I22
A23: 3 | B23: ='Location 3'!R1 | C23: 1 | D23: 1 | E23: 1 | F23: =C23*D23*E23 | G23: ='Location 3'!P73 | H23: =(F23*G23) | I23: 1 | J23: =H23/I23
A24: 4 | B24: ='Location 4'!R1 | C24: 1 | D24: 1 | E24: 1 | F24: =C24*D24*E24 | G24: ='Location 4'!P73 | H24: =(F24*G24) | I24: 1 | J24: =H24/I24
A25: 5 | B25: ='Location 5'!R1 | C25: 1 | D25: 1 | E25: 1 | F25: =C25*D25*E25 | G25: ='Location 5'!P73 | H25: =(F25*G25) | I25: 1 | J25: =H25/I25
A26: 6 | B26: ='Location 6'!R1 | C26: 1 | D26: 1 | E26: 1 | F26: =C26*D26*E26 | G26: ='Location 6'!P73 | H26: =(F26*G26) | I26: 1 | J26: =H26/I26
A27: Subtotal Subcontractors | H27: =SUM(H21:H26) | J27: =SUM(J21:J26)
A28: Optional Work
A29: Item | B29: Material Item | C29: Surcharge | D29: Units | E29: Other | F29: Total Surcharge | G29: Unit Price | H29: Subtotal 1 | I29: Margin | J29: Subtotal 2
A30: 1 | B30: ='Option 1'!R1 | C30: 1 | D30: 1 | E30: 1 | F30: =C30*D30*E30 | G30: ='Option 1'!P73 | H30: =C30*D30*E30*F30*G30 | I30: 1 | J30: =H30/I30
F31: =C31*D31*E31 | H31: =C31*D31*E31*F31*G31 | I31: 1 | J31: =H31/I31
A32: Subtotal Materials and Equipment | H32: =SUM(H30:H31) | J32: =SUM(J30:J31)
A35: Project Subtotal | J35: =J18+J27
A37: Cash Allowance | J37: 0
A39: Utility Isolation | J39: 0
A41: Discount | J41: 0
A43: Project Options Subtotal | J43: =(J32)
A45: Project Total | J45: =J35+J37+J39+J41+J43
A46: HST | J46: =J45*0.13
A47: TOTAL | J47: =J45+J46
A48: HST Check for final price should be the same as above | J48: =J45*1.13
G52: Cost Analysis | J52: Price
G53: Ainsworth | J53: =J45
G54: Company A
G55: Company B
G56: Company C
G57: Company D
B60: APS (Cost) | C60: Regular | D60: Regular W/truck | F60: Double Time | G60: Double Time W/truck | H60: Shift 20% | I60: Shift 20% W/truck
B61: FOREMAN | C61: 98.21 | D61: =(C61+17) | F61: 196.41 | G61: =(F61+17) | H61: 112.94 | I61: =H61+17
B62: JOURNEYMAN | C62: 87.65 | D62: =(C62+17) | F62: 175.31 | G62: =(F62+17) | H62: 100.8 | I62: =H62+17
B63: APPRENTICE #5 | C63: 71.38 | D63: =(C63+17) | F63: 142.73 | G63: =(F63+17) | H63: 82.09 | I63: =H63+17
B64: APPRENTICE #4 | C64: 63.34 | D64: =(C64+17) | F64: 126.7 | G64: =(F64+17) | H64: 72.84 | I64: =H64+17
B65: APPRENTICE #3 | C65: 55.33 | D65: =(C65+17) | F65: 110.64 | G65: =(F65+17) | H65: 63.63 | I65: =H65+17
B66: APPRENTICE #2 | C66: 47.3 | D66: =(C66+17) | F66: 94.59 | G66: =(F66+17) | H66: 54.4 | I66: =H66+17
B67: APPRENTICE #1 | C67: 39.25 | D67: =(C67+17) | F67: 78.49 | G67: =(F67+17) | H67: 45.14 | I67: =H67+17
B69: APS (Sell) | C69: Regular | D69: Regular W/truck | F69: Double Time | G69: Double Time W/truck | H69: Shift 20% | I69: Shift 20% W/truck | K69: Margin
B70: FOREMAN | C70: =C61/$K$70 | D70: =D61/$K$70 | F70: =F61/$K$70 | G70: =G61/$K$70 | H70: =H61/$K$70 | I70: =I61/$K$70 | K70: 0.8
B71: JOURNEYMAN | C71: =C62/$K$70 | D71: =D62/$K$70 | F71: =F62/$K$70 | G71: =G62/$K$70 | H71: =H62/$K$70 | I71: =I62/$K$70
B72: APPRENTICE #5 | C72: =C63/$K$70 | D72: =D63/$K$70 | F72: =F63/$K$70 | G72: =G63/$K$70 | H72: =H63/$K$70 | I72: =I63/$K$70
B73: APPRENTICE #4 | C73: =C64/$K$70 | D73: =D64/$K$70 | F73: =F64/$K$70 | G73: =G64/$K$70 | H73: =H64/$K$70 | I73: =I64/$K$70
B74: APPRENTICE #3 | C74: =C65/$K$70 | D74: =D65/$K$70 | F74: =F65/$K$70 | G74: =G65/$K$70 | H74: =H65/$K$70 | I74: =I65/$K$70
B75: APPRENTICE #2 | C75: =C66/$K$70 | D75: =D66/$K$70 | F75: =F66/$K$70 | G75: =G66/$K$70 | H75: =H66/$K$70 | I75: =I66/$K$70
B76: APPRENTICE #1 | C76: =C67/$K$70 | D76: =D67/$K$70 | F76: =F67/$K$70 | G76: =G67/$K$70 | H76: =H67/$K$70 | I76: =I67/$K$70
B79: Bonding | C79: rate/Moths
B80: First $2.5M | C80: 8.7 | G80: 2500000 | I80: =G80/1000*C80
B81: Second $2.5M | C81: 7.9 | G81: 2500000 | I81: =G81/1000*C81
B82: Third $2.5M | C82: 6.95 | G82: 2500000 | I82: =G82/1000*C82
B83: Subtotal | I83: =I80+I81+I82
B84: after 24 months | C84: 12 | I84: =I83*C84*0.01
B85: Grand Total for Bond | I85: =I83+I84
B86: Sell Price | I86: =I85/0.9

Sheet Location 1
A1: {=MID(CELL("filename",C1),FIND("]",CELL("filename",C1))+1,255)} | R1: {=MID(CELL("filename",C1),FIND("]",CELL("filename",C1))+1,255)}
A3: AINSWORTH LABOUR
A4: Item | B4: Task | C4: Regular Labour Rates | I4: Premium Labour Rates | O4: Margin | P4: Subtotal 3 - Sell Rate
C5: # of techs | D5: Days/Units | E5: Regular Hours | F5: Total Regular Hours | G5: Regular Labour Rate | H5: Subtotal 1 | I5: # of techs | J5: Days/Units | K5: O/T Hours | L5: Total O/T Hours | M5: O/T Labour Rate | N5: Subtotal 2
A6: Project Management | T6: =(P26+P37+P42)*0.05
A7: 1 | B7: Engineering/Meetings | C7: 0 | D7: 0 | F7: =C7*D7*E7 | G7: 90 | H7: =F7*G7 | L7: =I7*J7*K7 | M7: 150 | N7: =L7*M7 | O7: 0.85 | P7: =H7/O7+N7/O7
A8: 2 | B8: Project Management | C8: 0 | D8: 1 | E8: 1 | F8: =C8*D8*E8 | G8: =(P26+P37+P42) | H8: =F8*G8 | L8: =I8*J8*K8 | M8: 150 | N8: =L8*M8 | O8: 0.85 | P8: =H8/O8+N8/O8
A9: 3 | B9: ESA Submissions | C9: 1 | D9: 1 | E9: 1 | F9: =C9*D9*E9 | G9: 250 | H9: =F9*G9 | L9: =I9*J9*K9 | M9: 0 | N9: =L9*M9 | O9: 0.85 | P9: =H9/O9+N9/O9
A10: 4 | B10: Misc. Subcontractors | C10: 0 | D10: 1 | E10: 1 | F10: =C10*D10*E10 | G10: =P37 | H10: =F10*G10 | L10: =I10*J10*K10 | M10: 150 | N10: =L10*M10 | O10: 0.85 | P10: =H10/O10+N10/O10
A11: 5 | B11: Misc. Materials | C11: 0 | D11: 1 | E11: 1 | F11: =C11*D11*E11 | G11: =P42 | H11: =F11*G11 | L11: =I11*J11*K11 | M11: 150 | N11: =L11*M11 | O11: 0.85 | P11: =H11/O11+N11/O11
A12: 6 | B12: Forman - site supervision and civil | F12: =C12*D12*E12 | G12: 92 | H12: =F12*G12 | L12: =I12*J12*K12 | M12: 150 | N12: =L12*M12 | O12: 0.85 | P12: =H12/O12+N12/O12
A13: 7 | B13: Lodging | C13: 1 | D13: 1 | E13: 1 | F13: =C13*D13*E13 | G13: 0 | H13: =F13*G13 | L13: =I13*J13*K13 | M13: 175 | N13: =L13*M13 | O13: 0.85 | P13: =H13/O13+N13/O13
A14: Total Management | F14: =SUM(F7:F13) | H14: =SUM(H7:H13) | L14: =SUM(L7:L13) | N14: =SUM(N7:N13) | P14: =SUM(P7:P13)
A16: Labour
A17: 1 | B17: Switching | F17: =C17*D17*E17 | G17: 108 | H17: =F17*G17 | L17: =I17*J17*K17 | M17: 195 | N17: =L17*M17 | O17: 0.85 | P17: =H17/O17+N17/O17
A18: 2 | B18: 16 kV Breakers: Four (4) Siemens vacuum type breakers M13-1, M13-3, M13-4 and M13-6 | F18: =C18*D18*E18 | G18: 108 | H18: =F18*G18 | L18: =I18*J18*K18 | M18: 195 | N18: =L18*M18 | O18: 0.85 | P18: =H18/O18+N18/O18
A19: 3 | B19: 2500 KVA transformer (CUB-T1) | F19: =C19*D19*E19 | G19: 108 | H19: =F19*G19 | L19: =I19*J19*K19 | M19: 195 | N19: =L19*M19 | O19: 0.85 | P19: =H19/O19+N19/O19
A20: 4 | B20: Switchgear CUB SWGR 600 Volt Cutler-Hammer Drawout Magnum Main | F20: =C20*D20*E20 | G20: 108 | H20: =F20*G20 | L20: =I20*J20*K20 | M20: 195 | N20: =L20*M20 | O20: 0.85 | P20: =H20/O20+N20/O20
A21: 5 | B21: 2500 KVA transformer (CUB-T2) | F21: =C21*D21*E21 | G21: 108 | H21: =F21*G21 | L21: =I21*J21*K21 | M21: 195 | N21: =L21*M21 | O21: 0.85 | P21: =H21/O21+N21/O21
A22: 6 | B22: 8200 KVA CUB Cogen transformer | F22: =C22*D22*E22 | G22: 108 | H22: =F22*G22 | L22: =I22*J22*K22 | M22: 195 | N22: =L22*M22 | O22: 0.85 | P22: =H22/O22+N22/O22
A23: 7 | B23: 5 kV Breakers: Four (4) Square vacuum type breakers | F23: =C23*D23*E23 | G23: 108 | H23: =F23*G23 | L23: =I23*J23*K23 | M23: 195 | N23: =L23*M23 | O23: 0.85 | P23: =H23/O23+N23/O23
A24: 8 | B24: 750 kVA Black Start transformer | F24: =C24*D24*E24 | G24: 108 | L24: =I24*J24*K24 | M24: 195
A25: 9 | B25: Pole Work | F25: =C25*D25*E25 | G25: 108 | H25: =F25*G25 | L25: =I25*J25*K25 | M25: 195 | N25: =L25*M25 | O25: 0.85 | P25: =H25/O25+N25/O25
A26: Sub Total Labour | F26: =SUM(F17:F25) | H26: =SUM(H17:H25) | L26: =SUM(L17:L25) | N26: =SUM(N17:N25) | P26: =SUM(P17:P25)
A27: Subtotal Labour | F27: =F14+F26 | H27: =H14+H26 | L27: =L14+L26 | N27: =N14+N26 | P27: =P14+P26
A28: Subcontractors
A29: Item | B29: Task | C29: Surcharge | E29: Days/Units | G29: Other | I29: Total Surcharge | K29: Unit Price | M29: Subtotal 1 | O29: Margin | P29: Subtotal 2
A30: 1 | B30: Alectra | C30: 1 | E30: 1 | G30: 1 | I30: =C30*E30*G30 | K30: 2000 | M30: =K30*I30 | O30: 0.9 | P30: =M30/O30
A31: 2 | B31: parking | I31: =C31*E31*G31 | M31: =K31*I31 | O31: 0.85 | P31: =M31/O31
A32: 3 | B32: Millwrighting | I32: =C32*E32*G32 | M32: =K32*I32 | O32: 0.85 | P32: =M32/O32
A33: 4 | B33: Temp Door | I33: =C33*E33*G33 | M33: =K33*I33 | O33: 0.85 | P33: =M33/O33
A34: 5 | B34: Bonding Costs | I34: =C34*E34*G34 | M34: =K34*I34 | O34: 0.85 | P34: =M34/O34
I35: =C35*E35*G35 | M35: =K35*I35 | O35: 0.85 | P35: =M35/O35
I36: =C36*E36*G36 | M36: =K36*I36 | O36: 0.85 | P36: =M36/O36
A37: Subtotal Subcontractors | P37: =SUM(P30:P36)
A38: Materials and Equipment
A39: Item | B39: Material Item | C39: Surcharge | E39: Units/Length | G39: Other | I39: Total Surcharge | K39: Unit Price | M39: Subtotal 1 | O39: Margin | P39: Subtotal 2
A40: 1 | B40: Batteries | C40: 1 | E40: 10 | G40: 1 | I40: =G40*E40*C40 | K40: 12 | M40: =K40*I40 | O40: 0.85 | P40: =M40/O40
A41: 2 | I41: =G41*E41*C41 | M41: =K41*I41 | O41: 0.85 | P41: =M41/O41
A42: Subtotal Materials and Equipment | P42: =SUM(P40:P41)
A45: Project Subtotal | P45: =P27+P37+P42
A47: Cash Allowance | P47: 0
A49: Utility Isolation | P49: 0
A51: Discount | P51: 0
A53: Project Total | P53: =SUM(P45,P47,P49, P51)
A54: HST | P54: =P53*0.13
A55: TOTAL | P55: =P53+P54
A56: HST Check for final price should be the same as above | P56: =P53*1.13
B61: APS (Cost) | C61: Regular | D61: Regular W/truck | F61: Double Time | G61: Double Time W/truck | H61: Shift 20% | I61: Shift 20% W/truck
B62: FOREMAN | C62: 102 | D62: =(C62+18.5) | F62: 203.99 | G62: =(F62+18.5) | H62: 122.38 | I62: =H62+18.5
B63: JOURNEYMAN | C63: 90.93 | D63: =(C63+18.5) | F63: 181.86 | G63: =(F63+18.5) | H63: 109.13 | I63: =H63+18.5
B64: APPRENTICE #5 | C64: 74.01 | D64: =(C64+18.5) | F64: 147.98 | G64: =(F64+18.5) | H64: 88.78 | I64: =H64+18.5
B65: APPRENTICE #4 | C65: 65.65 | D65: =(C65+18.5) | F65: 131.3 | G65: =(F65+18.5) | H65: 78.79 | I65: =H65+18.5
B66: APPRENTICE #3 | C66: 57.28 | D66: =(C66+18.5) | F66: 114.57 | G66: =(F66+18.5) | H66: 68.74 | I66: =H66+18.5
B67: APPRENTICE #2 | C67: 48.95 | D67: =(C67+18.5) | F67: 97.85 | G67: =(F67+18.5) | H67: 58.71 | I67: =H67+18.5
B68: APPRENTICE #1 | C68: 40.57 | D68: =(C68+18.5) | F68: 81.15 | G68: =(F68+18.5) | H68: 48.69 | I68: =H68+18.5
B69: pre apprentice | C69: 32.43 | D69: =(C69+18.5) | F69: 64.86 | G69: =(F69+18.5) | H69: 38.92 | I69: =H69+18.5
B71: APS (Sell) | C71: Regular | D71: Regular W/truck | F71: Double Time | G71: Double Time W/truck | H71: Shift 20% | I71: Shift 20% W/truck | K71: Margin
B72: FOREMAN | C72: =C62/$K$72 | D72: =D62/$K$72 | F72: =F62/$K$72 | G72: =G62/$K$72 | H72: =H62/$K$72 | I72: =I62/$K$72 | K72: 0.8
B73: JOURNEYMAN | C73: =C63/$K$72 | D73: =D63/$K$72 | F73: =F63/$K$72 | G73: =G63/$K$72 | H73: =H63/$K$72 | I73: =I63/$K$72
B74: APPRENTICE #5 | C74: =C64/$K$72 | D74: =D64/$K$72 | F74: =F64/$K$72 | G74: =G64/$K$72 | H74: =H64/$K$72 | I74: =I64/$K$72
B75: APPRENTICE #4 | C75: =C65/$K$72 | D75: =D65/$K$72 | F75: =F65/$K$72 | G75: =G65/$K$72 | H75: =H65/$K$72 | I75: =I65/$K$72
B76: APPRENTICE #3 | C76: =C66/$K$72 | D76: =D66/$K$72 | F76: =F66/$K$72 | G76: =G66/$K$72 | H76: =H66/$K$72 | I76: =I66/$K$72
B77: APPRENTICE #2 | C77: =C67/$K$72 | D77: =D67/$K$72 | F77: =F67/$K$72 | G77: =G67/$K$72 | H77: =H67/$K$72 | I77: =I67/$K$72
B78: APPRENTICE #1 | C78: =C68/$K$72 | D78: =D68/$K$72 | F78: =F68/$K$72 | G78: =G68/$K$72 | H78: =H68/$K$72 | I78: =I68/$K$72
B79: pre apprentice | C79: =C69/$K$72 | D79: =D69/$K$72 | F79: =F69/$K$72 | G79: =G69/$K$72 | H79: =H69/$K$72 | I79: =I69/$K$72
B82: Bonding | C82: rate/Moths
B83: First $2.5M | C83: 8.7 | G83: 2500000 | I83: =G83/1000*C83
B84: Second $2.5M | C84: 7.9 | G84: 2500000 | I84: =G84/1000*C84
B85: Third $2.5M | C85: 6.95 | G85: 2500000 | I85: =G85/1000*C85
B86: Subtotal | I86: =I83+I84+I85
B87: after 24 months | C87: 12 | I87: =I86*C87*0.01
B88: Grand Total for Bond | I88: =I86+I87
B89: Sell Price | I89: =I88/0.9

Sheet Location 2
A1: {=MID(CELL("filename",C1),FIND("]",CELL("filename",C1))+1,255)} | R1: {=MID(CELL("filename",C1),FIND("]",CELL("filename",C1))+1,255)}
A3: AINSWORTH LABOUR
A4: Item | B4: Task | C4: Regular Labour Rates | I4: Premium Labour Rates | O4: Margin | P4: Subtotal 3 - Sell Rate
C5: # of techs | D5: Days/Units | E5: Regular Hours | F5: Total Regular Hours | G5: Regular Labour Rate | H5: Subtotal 1 | I5: # of techs | J5: Days/Units | K5: O/T Hours | L5: Total O/T Hours | M5: O/T Labour Rate | N5: Subtotal 2
A6: Project Management | T6: =(P22+P33+P44)*0.05
A7: 1 | B7: Engineering/Meetings | C7: 0 | D7: 0 | F7: =C7*D7*E7 | G7: 90 | H7: =F7*G7 | L7: =I7*J7*K7 | M7: 150 | N7: =L7*M7 | O7: 0.85 | P7: =H7/O7+N7/O7
A8: 2 | B8: Project Management | C8: 0.05 | D8: 1 | E8: 1 | F8: =C8*D8*E8 | G8: =(P22+P33+P44) | H8: =F8*G8 | L8: =I8*J8*K8 | M8: 150 | N8: =L8*M8 | O8: 0.85 | P8: =H8/O8+N8/O8
A9: 3 | B9: ESA Submissions | F9: =C9*D9*E9 | G9: 2000 | H9: =F9*G9 | L9: =I9*J9*K9 | M9: 0 | N9: =L9*M9 | O9: 0.85 | P9: =H9/O9+N9/O9
A10: 4 | B10: Misc. Subcontractors | C10: 0.05 | D10: 1 | E10: 1 | F10: =C10*D10*E10 | G10: =P33 | H10: =F10*G10 | L10: =I10*J10*K10 | M10: 150 | N10: =L10*M10 | O10: 0.85 | P10: =H10/O10+N10/O10
A11: 5 | B11: Misc. Materials | C11: 0.05 | D11: 1 | E11: 1 | F11: =C11*D11*E11 | G11: =P44 | H11: =F11*G11 | L11: =I11*J11*K11 | M11: 150 | N11: =L11*M11 | O11: 0.85 | P11: =H11/O11+N11/O11
A12: 6 | B12: Forman - site supervision and civil | F12: =C12*D12*E12 | G12: 92 | H12: =F12*G12 | L12: =I12*J12*K12 | M12: 150 | N12: =L12*M12 | O12: 0.85 | P12: =H12/O12+N12/O12
A13: 7 | B13: Lodging | C13: 1 | D13: 1 | E13: 1 | F13: =C13*D13*E13 | G13: 0 | H13: =F13*G13 | L13: =I13*J13*K13 | M13: 175 | N13: =L13*M13 | O13: 0.85 | P13: =H13/O13+N13/O13
A14: Total Management | F14: =SUM(F7:F13) | H14: =SUM(H7:H13) | L14: =SUM(L7:L13) | N14: =SUM(N7:N13) | P14: =SUM(P7:P13)
A16: Labour
A17: 1 | B17: Mob/demob | F17: =C17*D17*E17 | G17: 108 | H17: =F17*G17 | L17: =I17*J17*K17 | M17: 195 | N17: =L17*M17 | O17: 0.85 | P17: =H17/O17+N17/O17
A18: 2 | B18: install | F18: =C18*D18*E18 | G18: 108 | H18: =F18*G18 | L18: =I18*J18*K18 | M18: 195 | N18: =L18*M18 | O18: 0.85 | P18: =H18/O18+N18/O18
A19: 3 | B19: assist | F19: =C19*D19*E19 | G19: 108 | H19: =F19*G19 | L19: =I19*J19*K19 | M19: 195 | N19: =L19*M19 | O19: 0.85 | P19: =H19/O19+N19/O19
A20: 4 | F20: =C20*D20*E20 | G20: 108 | H20: =F20*G20 | L20: =I20*J20*K20 | M20: 195 | N20: =L20*M20 | O20: 0.85 | P20: =H20/O20+N20/O20
A21: 9 | F21: =C21*D21*E21 | G21: 108 | H21: =F21*G21 | L21: =I21*J21*K21 | M21: 195 | N21: =L21*M21 | O21: 0.85 | P21: =H21/O21+N21/O21
A22: Sub Total Labour | F22: =SUM(F17:F21) | H22: =SUM(H17:H21) | L22: =SUM(L17:L21) | N22: =SUM(N17:N21) | P22: =SUM(P17:P21)
A23: Subtotal Labour | F23: =F14+F22 | H23: =H14+H22 | L23: =L14+L22 | N23: =N14+N22 | P23: =P14+P22
A24: Subcontractors
A25: Item | B25: Task | C25: Surcharge | E25: Days/Units | G25: Other | I25: Total Surcharge | K25: Unit Price | M25: Subtotal 1 | O25: Margin | P25: Subtotal 2
A26: 1 | B26: MG Power and Associates Inc | I26: =C26*E26*G26 | M26: =K26*I26 | O26: 0.85 | P26: =M26/O26
A27: 2 | B27: parking | I27: =C27*E27*G27 | M27: =K27*I27 | O27: 0.85 | P27: =M27/O27
A28: 3 | B28: Millwrighting | I28: =C28*E28*G28 | M28: =K28*I28 | O28: 0.85 | P28: =M28/O28
A29: 4 | B29: Temp Door | I29: =C29*E29*G29 | M29: =K29*I29 | O29: 0.85 | P29: =M29/O29
A30: 5 | B30: Bonding Costs | I30: =C30*E30*G30 | M30: =K30*I30 | O30: 0.85 | P30: =M30/O30
I31: =C31*E31*G31 | M31: =K31*I31 | O31: 0.85 | P31: =M31/O31
I32: =C32*E32*G32 | M32: =K32*I32 | O32: 0.85 | P32: =M32/O32
A33: Subtotal Subcontractors | P33: =SUM(P26:P32)
A34: Materials and Equipment
A35: Item | B35: Material Item | C35: Surcharge | E35: Units/Length | G35: Other | I35: Total Surcharge | K35: Unit Price | M35: Subtotal 1 | O35: Margin | P35: Subtotal 2
A36: 1 | B36: ABB SWGR | I36: =G36*E36*C36 | M36: =K36*I36 | O36: 0.85 | P36: =M36/O36
A37: 2 | B37: parking | I37: =G37*E37*C37 | M37: =K37*I37 | O37: 0.85 | P37: =M37/O37
A38: 18 | B38: AS-7096N Sealant | I38: =G38*E38*C38 | M38: =K38*I38 | O38: 0.85 | P38: =M38/O38
A39: 19 | B39: Breaker HLL36060 | I39: =G39*E39*C39 | M39: =K39*I39 | O39: 0.85 | P39: =M39/O39
A40: 20 | B40: Pull Box, EEMAC-1 300mX300mmX150mm (P/N: CS12126) | I40: =G40*E40*C40 | M40: =K40*I40 | O40: 0.85 | P40: =M40/O40
A41: 27 | B41: Aluminum Bracket (Aluma Form) | I41: =G41*E41*C41 | M41: =K41*I41 | O41: 0.85 | P41: =M41/O41
A42: 28 | I42: =G42*E42*C42 | M42: =K42*I42 | O42: 0.85 | P42: =M42/O42
A43: 29 | I43: =G43*E43*C43 | M43: =K43*I43 | O43: 0.85 | P43: =M43/O43
A44: Subtotal Materials and Equipment | P44: =SUM(P36:P43)
A47: Project Subtotal | P47: =P23+P33+P44
A49: Cash Allowance | P49: 0
A51: Utility Isolation | P51: 0
A53: Discount | P53: 0
A55: Project Total | P55: =SUM(P47,P49,P51, P53)
A56: HST | P56: =P55*0.13
A57: TOTAL | P57: =P55+P56
A58: HST Check for final price should be the same as above | P58: =P55*1.13
B73: APS (Cost) | C73: Regular | D73: Regular W/truck | F73: Double Time | G73: Double Time W/truck | H73: Shift 20% | I73: Shift 20% W/truck
B74: FOREMAN | C74: 102 | D74: =(C74+18.5) | F74: 203.99 | G74: =(F74+18.5) | H74: 122.38 | I74: =H74+18.5
B75: JOURNEYMAN | C75: 90.93 | D75: =(C75+18.5) | F75: 181.86 | G75: =(F75+18.5) | H75: 109.13 | I75: =H75+18.5
B76: APPRENTICE #5 | C76: 74.01 | D76: =(C76+18.5) | F76: 147.98 | G76: =(F76+18.5) | H76: 88.78 | I76: =H76+18.5
B77: APPRENTICE #4 | C77: 65.65 | D77: =(C77+18.5) | F77: 131.3 | G77: =(F77+18.5) | H77: 78.79 | I77: =H77+18.5
B78: APPRENTICE #3 | C78: 57.28 | D78: =(C78+18.5) | F78: 114.57 | G78: =(F78+18.5) | H78: 68.74 | I78: =H78+18.5
B79: APPRENTICE #2 | C79: 48.95 | D79: =(C79+18.5) | F79: 97.85 | G79: =(F79+18.5) | H79: 58.71 | I79: =H79+18.5
B80: APPRENTICE #1 | C80: 40.57 | D80: =(C80+18.5) | F80: 81.15 | G80: =(F80+18.5) | H80: 48.69 | I80: =H80+18.5
B81: pre apprentice | C81: 32.43 | D81: =(C81+18.5) | F81: 64.86 | G81: =(F81+18.5) | H81: 38.92 | I81: =H81+18.5
B83: APS (Sell) | C83: Regular | D83: Regular W/truck | F83: Double Time | G83: Double Time W/truck | H83: Shift 20% | I83: Shift 20% W/truck | K83: Margin
B84: FOREMAN | C84: =C74/$K$84 | D84: =D74/$K$84 | F84: =F74/$K$84 | G84: =G74/$K$84 | H84: =H74/$K$84 | I84: =I74/$K$84 | K84: 0.8
B85: JOURNEYMAN | C85: =C75/$K$84 | D85: =D75/$K$84 | F85: =F75/$K$84 | G85: =G75/$K$84 | H85: =H75/$K$84 | I85: =I75/$K$84
B86: APPRENTICE #5 | C86: =C76/$K$84 | D86: =D76/$K$84 | F86: =F76/$K$84 | G86: =G76/$K$84 | H86: =H76/$K$84 | I86: =I76/$K$84
B87: APPRENTICE #4 | C87: =C77/$K$84 | D87: =D77/$K$84 | F87: =F77/$K$84 | G87: =G77/$K$84 | H87: =H77/$K$84 | I87: =I77/$K$84
B88: APPRENTICE #3 | C88: =C78/$K$84 | D88: =D78/$K$84 | F88: =F78/$K$84 | G88: =G78/$K$84 | H88: =H78/$K$84 | I88: =I78/$K$84
B89: APPRENTICE #2 | C89: =C79/$K$84 | D89: =D79/$K$84 | F89: =F79/$K$84 | G89: =G79/$K$84 | H89: =H79/$K$84 | I89: =I79/$K$84
B90: APPRENTICE #1 | C90: =C80/$K$84 | D90: =D80/$K$84 | F90: =F80/$K$84 | G90: =G80/$K$84 | H90: =H80/$K$84 | I90: =I80/$K$84
B91: pre apprentice | C91: =C81/$K$84 | D91: =D81/$K$84 | F91: =F81/$K$84 | G91: =G81/$K$84 | H91: =H81/$K$84 | I91: =I81/$K$84
B94: Bonding | C94: rate/Moths
B95: First $2.5M | C95: 8.7 | G95: 2500000 | I95: =G95/1000*C95
B96: Second $2.5M | C96: 7.9 | G96: 2500000 | I96: =G96/1000*C96
B97: Third $2.5M | C97: 6.95 | G97: 2500000 | I97: =G97/1000*C97
B98: Subtotal | I98: =I95+I96+I97
B99: after 24 months | C99: 12 | I99: =I98*C99*0.01
B100: Grand Total for Bond | I100: =I98+I99
B101: Sell Price | I101: =I100/0.9

Sheet Location 3
A1: {=MID(CELL("filename",C1),FIND("]",CELL("filename",C1))+1,255)} | R1: {=MID(CELL("filename",C1),FIND("]",CELL("filename",C1))+1,255)}
A3: AINSWORTH LABOUR
A4: Item | B4: Task | C4: Regular Labour Rates | I4: Premium Labour Rates | O4: Margin | P4: Subtotal 3 - Sell Rate
C5: # of techs | D5: Days/Units | E5: Regular Hours | F5: Total Regular Hours | G5: Regular Labour Rate | H5: Subtotal 1 | I5: # of techs | J5: Days/Units | K5: O/T Hours | L5: Total O/T Hours | M5: O/T Labour Rate | N5: Subtotal 2
A6: Project Management | T6: =(P25+P36+P62)*0.05
A7: 1 | B7: Engineering/Meetings | C7: 0 | D7: 0 | F7: =C7*D7*E7 | G7: 90 | H7: =F7*G7 | L7: =I7*J7*K7 | M7: 150 | N7: =L7*M7 | O7: 0.85 | P7: =H7/O7+N7/O7
A8: 2 | B8: Project Management | C8: 0.05 | D8: 1 | E8: 1 | F8: =C8*D8*E8 | G8: =(P25+P36+P62) | H8: =F8*G8 | L8: =I8*J8*K8 | M8: 150 | N8: =L8*M8 | O8: 0.85 | P8: =H8/O8+N8/O8
A9: 3 | B9: ESA Submissions | F9: =C9*D9*E9 | G9: 2000 | H9: =F9*G9 | L9: =I9*J9*K9 | M9: 0 | N9: =L9*M9 | O9: 0.85 | P9: =H9/O9+N9/O9
A10: 4 | B10: Misc. Subcontractors | C10: 0.05 | D10: 1 | E10: 1 | F10: =C10*D10*E10 | G10: =P36 | H10: =F10*G10 | L10: =I10*J10*K10 | M10: 150 | N10: =L10*M10 | O10: 0.85 | P10: =H10/O10+N10/O10
A11: 5 | B11: Misc. Materials | C11: 0.05 | D11: 1 | E11: 1 | F11: =C11*D11*E11 | G11: =P62 | H11: =F11*G11 | L11: =I11*J11*K11 | M11: 150 | N11: =L11*M11 | O11: 0.85 | P11: =H11/O11+N11/O11
A12: 6 | B12: Forman - site supervision and civil | F12: =C12*D12*E12 | G12: 92 | H12: =F12*G12 | L12: =I12*J12*K12 | M12: 150 | N12: =L12*M12 | O12: 0.85 | P12: =H12/O12+N12/O12
A13: 7 | B13: Lodging | C13: 1 | D13: 1 | E13: 1 | F13: =C13*D13*E13 | G13: 0 | H13: =F13*G13 | L13: =I13*J13*K13 | M13: 175 | N13: =L13*M13 | O13: 0.85 | P13: =H13/O13+N13/O13
A14: Total Management | F14: =SUM(F7:F13) | H14: =SUM(H7:H13) | L14: =SUM(L7:L13) | N14: =SUM(N7:N13) | P14: =SUM(P7:P13)
A16: Labour
A17: 1 | B17: Mob/demob | F17: =C17*D17*E17 | G17: 108 | H17: =F17*G17 | L17: =I17*J17*K17 | M17: 195 | N17: =L17*M17 | O17: 0.85 | P17: =H17/O17+N17/O17
A18: 2 | B18: install | F18: =C18*D18*E18 | G18: 108 | H18: =F18*G18 | L18: =I18*J18*K18 | M18: 195 | N18: =L18*M18 | O18: 0.85 | P18: =H18/O18+N18/O18
A19: 3 | B19: assist | F19: =C19*D19*E19 | G19: 108 | H19: =F19*G19 | L19: =I19*J19*K19 | M19: 195 | N19: =L19*M19 | O19: 0.85 | P19: =H19/O19+N19/O19
A20: 4 | F20: =C20*D20*E20 | G20: 108 | H20: =F20*G20 | L20: =I20*J20*K20 | M20: 195 | N20: =L20*M20 | O20: 0.85 | P20: =H20/O20+N20/O20
A21: 5 | F21: =C21*D21*E21 | G21: 108 | H21: =F21*G21 | L21: =I21*J21*K21 | M21: 195 | N21: =L21*M21 | O21: 0.85 | P21: =H21/O21+N21/O21
A22: 6 | F22: =C22*D22*E22 | G22: 108 | H22: =F22*G22 | L22: =I22*J22*K22 | M22: 195 | N22: =L22*M22 | O22: 0.85 | P22: =H22/O22+N22/O22
A23: 7 | F23: =C23*D23*E23 | G23: 108 | H23: =F23*G23 | L23: =I23*J23*K23 | M23: 195 | N23: =L23*M23 | O23: 0.85 | P23: =H23/O23+N23/O23
A24: 8 | F24: =C24*D24*E24 | G24: 108 | H24: =F24*G24 | L24: =I24*J24*K24 | M24: 195 | N24: =L24*M24 | O24: 0.85 | P24: =H24/O24+N24/O24
A25: Sub Total Labour | F25: =SUM(F17:F24) | H25: =SUM(H17:H24) | L25: =SUM(L17:L24) | N25: =SUM(N17:N24) | P25: =SUM(P17:P24)
A26: Subtotal Labour | F26: =F14+F25 | H26: =H14+H25 | L26: =L14+L25 | N26: =N14+N25 | P26: =P14+P25
A27: Subcontractors
A28: Item | B28: Task | C28: Surcharge | E28: Days/Units | G28: Other | I28: Total Surcharge | K28: Unit Price | M28: Subtotal 1 | O28: Margin | P28: Subtotal 2
A29: 1 | B29: MG Power and Associates Inc | I29: =C29*E29*G29 | M29: =K29*I29 | O29: 0.85 | P29: =M29/O29
A30: 2 | B30: parking | I30: =C30*E30*G30 | M30: =K30*I30 | O30: 0.85 | P30: =M30/O30
A31: 3 | B31: Millwrighting | I31: =C31*E31*G31 | M31: =K31*I31 | O31: 0.85 | P31: =M31/O31
A32: 4 | B32: Temp Door | I32: =C32*E32*G32 | M32: =K32*I32 | O32: 0.85 | P32: =M32/O32
A33: 5 | B33: Bonding Costs | I33: =C33*E33*G33 | M33: =K33*I33 | O33: 0.85 | P33: =M33/O33
I34: =C34*E34*G34 | M34: =K34*I34 | O34: 0.85 | P34: =M34/O34
I35: =C35*E35*G35 | M35: =K35*I35 | O35: 0.85 | P35: =M35/O35
A36: Subtotal Subcontractors | P36: =SUM(P29:P35)
A37: Materials and Equipment
A38: Item | B38: Material Item | C38: Surcharge | E38: Units/Length | G38: Other | I38: Total Surcharge | K38: Unit Price | M38: Subtotal 1 | O38: Margin | P38: Subtotal 2
A39: 1 | B39: ABB SWGR | I39: =G39*E39*C39 | M39: =K39*I39 | O39: 0.85 | P39: =M39/O39
A40: 2 | B40: parking | I40: =G40*E40*C40 | M40: =K40*I40 | O40: 0.85 | P40: =M40/O40
A41: 3 | I41: =G41*E41*C41 | M41: =K41*I41 | O41: 0.85 | P41: =M41/O41
A42: 4 | I42: =G42*E42*C42 | M42: =K42*I42 | O42: 0.85 | P42: =M42/O42
A43: 5 | I43: =G43*E43*C43 | M43: =K43*I43 | O43: 0.85 | P43: =M43/O43
A44: 6 | I44: =G44*E44*C44 | M44: =K44*I44 | O44: 0.85 | P44: =M44/O44
A45: 7 | I45: =G45*E45*C45 | M45: =K45*I45 | O45: 0.85 | P45: =M45/O45
A46: 8 | I46: =G46*E46*C46 | M46: =K46*I46 | O46: 0.85 | P46: =M46/O46
A47: 9 | I47: =G47*E47*C47 | M47: =K47*I47 | O47: 0.85 | P47: =M47/O47
A48: 10 | I48: =G48*E48*C48 | M48: =K48*I48 | O48: 0.85 | P48: =M48/O48
A49: 11 | I49: =G49*E49*C49 | M49: =K49*I49 | O49: 0.85 | P49: =M49/O49
A50: 12 | I50: =G50*E50*C50 | M50: =K50*I50 | O50: 0.85 | P50: =M50/O50
A51: 13 | B51: Rigid 90deg - 2" | I51: =G51*E51*C51 | M51: =K51*I51 | O51: 0.85 | P51: =M51/O51
A52: 14 | B52: Rigid Bullet Hub Connectors - 2" and Nut | I52: =G52*E52*C52 | M52: =K52*I52 | O52: 0.85 | P52: =M52/O52
A53: 15 | B53: YGA282N - 2 Hole Lug, #4/o AWG | I53: =G53*E53*C53 | M53: =K53*I53 | O53: 0.85 | P53: =M53/O53
A54: 16 | B54: Mounting tape - VBH F-9473PB by 3M | I54: =G54*E54*C54 | M54: =K54*I54 | O54: 0.85 | P54: =M54/O54
A55: 17 | B55: Foam tape - VBH F-4910 by 3M | I55: =G55*E55*C55 | M55: =K55*I55 | O55: 0.85 | P55: =M55/O55
A56: 18 | B56: AS-7096N Sealant | I56: =G56*E56*C56 | M56: =K56*I56 | O56: 0.85 | P56: =M56/O56
A57: 19 | B57: Breaker HLL36060 | I57: =G57*E57*C57 | M57: =K57*I57 | O57: 0.85 | P57: =M57/O57
A58: 20 | B58: Pull Box, EEMAC-1 300mX300mmX150mm (P/N: CS12126) | I58: =G58*E58*C58 | M58: =K58*I58 | O58: 0.85 | P58: =M58/O58
A59: 27 | B59: Aluminum Bracket (Aluma Form) | I59: =G59*E59*C59 | M59: =K59*I59 | O59: 0.85 | P59: =M59/O59
A60: 28 | I60: =G60*E60*C60 | M60: =K60*I60 | O60: 0.85 | P60: =M60/O60
A61: 29 | I61: =G61*E61*C61 | M61: =K61*I61 | O61: 0.85 | P61: =M61/O61
A62: Subtotal Materials and Equipment | P62: =SUM(P39:P61)
A65: Project Subtotal | P65: =P26+P36+P62
A67: Cash Allowance | P67: 0
A69: Utility Isolation | P69: 0
A71: Discount | P71: 0
A73: Project Total | P73: =SUM(P65,P67,P69, P71)
A74: HST | P74: =P73*0.13
A75: TOTAL | P75: =P73+P74
A76: HST Check for final price should be the same as above | P76: =P73*1.13
B85: APS (Cost) | C85: Regular | D85: Regular W/truck | F85: Double Time | G85: Double Time W/truck | H85: Shift 20% | I85: Shift 20% W/truck
B86: FOREMAN | C86: 98.21 | D86: =(C86+17) | F86: 196.41 | G86: =(F86+17) | H86: 112.94 | I86: =H86+17
B87: JOURNEYMAN | C87: 87.65 | D87: =(C87+17) | F87: 175.31 | G87: =(F87+17) | H87: 100.8 | I87: =H87+17
B88: APPRENTICE #5 | C88: 71.38 | D88: =(C88+17) | F88: 142.73 | G88: =(F88+17) | H88: 82.09 | I88: =H88+17
B89: APPRENTICE #4 | C89: 63.34 | D89: =(C89+17) | F89: 126.7 | G89: =(F89+17) | H89: 72.84 | I89: =H89+17
B90: APPRENTICE #3 | C90: 55.33 | D90: =(C90+17) | F90: 110.64 | G90: =(F90+17) | H90: 63.63 | I90: =H90+17
B91: APPRENTICE #2 | C91: 47.3 | D91: =(C91+17) | F91: 94.59 | G91: =(F91+17) | H91: 54.4 | I91: =H91+17
B92: APPRENTICE #1 | C92: 39.25 | D92: =(C92+17) | F92: 78.49 | G92: =(F92+17) | H92: 45.14 | I92: =H92+17
B94: APS (Sell) | C94: Regular | D94: Regular W/truck | F94: Double Time | G94: Double Time W/truck | H94: Shift 20% | I94: Shift 20% W/truck | K94: Margin
B95: FOREMAN | C95: =C86/$K$95 | D95: =D86/$K$95 | F95: =F86/$K$95 | G95: =G86/$K$95 | H95: =H86/$K$95 | I95: =I86/$K$95 | K95: 0.8
B96: JOURNEYMAN | C96: =C87/$K$95 | D96: =D87/$K$95 | F96: =F87/$K$95 | G96: =G87/$K$95 | H96: =H87/$K$95 | I96: =I87/$K$95
B97: APPRENTICE #5 | C97: =C88/$K$95 | D97: =D88/$K$95 | F97: =F88/$K$95 | G97: =G88/$K$95 | H97: =H88/$K$95 | I97: =I88/$K$95
B98: APPRENTICE #4 | C98: =C89/$K$95 | D98: =D89/$K$95 | F98: =F89/$K$95 | G98: =G89/$K$95 | H98: =H89/$K$95 | I98: =I89/$K$95
B99: APPRENTICE #3 | C99: =C90/$K$95 | D99: =D90/$K$95 | F99: =F90/$K$95 | G99: =G90/$K$95 | H99: =H90/$K$95 | I99: =I90/$K$95
B100: APPRENTICE #2 | C100: =C91/$K$95 | D100: =D91/$K$95 | F100: =F91/$K$95 | G100: =G91/$K$95 | H100: =H91/$K$95 | I100: =I91/$K$95
B101: APPRENTICE #1 | C101: =C92/$K$95 | D101: =D92/$K$95 | F101: =F92/$K$95 | G101: =G92/$K$95 | H101: =H92/$K$95 | I101: =I92/$K$95
B104: Bonding | C104: rate/Moths
B105: First $2.5M | C105: 8.7 | G105: 2500000 | I105: =G105/1000*C105
B106: Second $2.5M | C106: 7.9 | G106: 2500000 | I106: =G106/1000*C106
B107: Third $2.5M | C107: 6.95 | G107: 2500000 | I107: =G107/1000*C107
B108: Subtotal | I108: =I105+I106+I107
B109: after 24 months | C109: 12 | I109: =I108*C109*0.01
B110: Grand Total for Bond | I110: =I108+I109
B111: Sell Price | I111: =I110/0.9

Sheet Location 4
A1: {=MID(CELL("filename",C1),FIND("]",CELL("filename",C1))+1,255)} | R1: {=MID(CELL("filename",C1),FIND("]",CELL("filename",C1))+1,255)}
A3: AINSWORTH LABOUR
A4: Item | B4: Task | C4: Regular Labour Rates | I4: Premium Labour Rates | O4: Margin | P4: Subtotal 3 - Sell Rate
C5: # of techs | D5: Days/Units | E5: Regular Hours | F5: Total Regular Hours | G5: Regular Labour Rate | H5: Subtotal 1 | I5: # of techs | J5: Days/Units | K5: O/T Hours | L5: Total O/T Hours | M5: O/T Labour Rate | N5: Subtotal 2
A6: Project Management | T6: =(P25+P36+P62)*0.05
A7: 1 | B7: Engineering/Meetings | C7: 0 | D7: 0 | F7: =C7*D7*E7 | G7: 90 | H7: =F7*G7 | L7: =I7*J7*K7 | M7: 150 | N7: =L7*M7 | O7: 0.85 | P7: =H7/O7+N7/O7
A8: 2 | B8: Project Management | C8: 0.05 | D8: 1 | E8: 1 | F8: =C8*D8*E8 | G8: =(P25+P36+P62) | H8: =F8*G8 | L8: =I8*J8*K8 | M8: 150 | N8: =L8*M8 | O8: 0.85 | P8: =H8/O8+N8/O8
A9: 3 | B9: ESA Submissions | F9: =C9*D9*E9 | G9: 2000 | H9: =F9*G9 | L9: =I9*J9*K9 | M9: 0 | N9: =L9*M9 | O9: 0.85 | P9: =H9/O9+N9/O9
A10: 4 | B10: Misc. Subcontractors | C10: 0.05 | D10: 1 | E10: 1 | F10: =C10*D10*E10 | G10: =P36 | H10: =F10*G10 | L10: =I10*J10*K10 | M10: 150 | N10: =L10*M10 | O10: 0.85 | P10: =H10/O10+N10/O10
A11: 5 | B11: Misc. Materials | C11: 0.05 | D11: 1 | E11: 1 | F11: =C11*D11*E11 | G11: =P62 | H11: =F11*G11 | L11: =I11*J11*K11 | M11: 150 | N11: =L11*M11 | O11: 0.85 | P11: =H11/O11+N11/O11
A12: 6 | B12: Forman - site supervision and civil | F12: =C12*D12*E12 | G12: 92 | H12: =F12*G12 | L12: =I12*J12*K12 | M12: 150 | N12: =L12*M12 | O12: 0.85 | P12: =H12/O12+N12/O12
A13: 7 | B13: Lodging | C13: 1 | D13: 1 | E13: 1 | F13: =C13*D13*E13 | G13: 0 | H13: =F13*G13 | L13: =I13*J13*K13 | M13: 175 | N13: =L13*M13 | O13: 0.85 | P13: =H13/O13+N13/O13
A14: Total Management | F14: =SUM(F7:F13) | H14: =SUM(H7:H13) | L14: =SUM(L7:L13) | N14: =SUM(N7:N13) | P14: =SUM(P7:P13)
A16: Labour
A17: 1 | B17: Mob/demob | F17: =C17*D17*E17 | G17: 108 | H17: =F17*G17 | L17: =I17*J17*K17 | M17: 195 | N17: =L17*M17 | O17: 0.85 | P17: =H17/O17+N17/O17
A18: 2 | B18: install | F18: =C18*D18*E18 | G18: 108 | H18: =F18*G18 | L18: =I18*J18*K18 | M18: 195 | N18: =L18*M18 | O18: 0.85 | P18: =H18/O18+N18/O18
A19: 3 | B19: assist | F19: =C19*D19*E19 | G19: 108 | H19: =F19*G19 | L19: =I19*J19*K19 | M19: 195 | N19: =L19*M19 | O19: 0.85 | P19: =H19/O19+N19/O19
A20: 4 | F20: =C20*D20*E20 | G20: 108 | H20: =F20*G20 | L20: =I20*J20*K20 | M20: 195 | N20: =L20*M20 | O20: 0.85 | P20: =H20/O20+N20/O20
A21: 5 | F21: =C21*D21*E21 | G21: 108 | H21: =F21*G21 | L21: =I21*J21*K21 | M21: 195 | N21: =L21*M21 | O21: 0.85 | P21: =H21/O21+N21/O21
A22: 6 | F22: =C22*D22*E22 | G22: 108 | H22: =F22*G22 | L22: =I22*J22*K22 | M22: 195 | N22: =L22*M22 | O22: 0.85 | P22: =H22/O22+N22/O22
A23: 7 | F23: =C23*D23*E23 | G23: 108 | H23: =F23*G23 | L23: =I23*J23*K23 | M23: 195 | N23: =L23*M23 | O23: 0.85 | P23: =H23/O23+N23/O23
A24: 8 | F24: =C24*D24*E24 | G24: 108 | H24: =F24*G24 | L24: =I24*J24*K24 | M24: 195 | N24: =L24*M24 | O24: 0.85 | P24: =H24/O24+N24/O24
A25: Sub Total Labour | F25: =SUM(F17:F24) | H25: =SUM(H17:H24) | L25: =SUM(L17:L24) | N25: =SUM(N17:N24) | P25: =SUM(P17:P24)
A26: Subtotal Labour | F26: =F14+F25 | H26: =H14+H25 | L26: =L14+L25 | N26: =N14+N25 | P26: =P14+P25
A27: Subcontractors
A28: Item | B28: Task | C28: Surcharge | E28: Days/Units | G28: Other | I28: Total Surcharge | K28: Unit Price | M28: Subtotal 1 | O28: Margin | P28: Subtotal 2
A29: 1 | B29: MG Power and Associates Inc | I29: =C29*E29*G29 | M29: =K29*I29 | O29: 0.85 | P29: =M29/O29
A30: 2 | B30: parking | I30: =C30*E30*G30 | M30: =K30*I30 | O30: 0.85 | P30: =M30/O30
A31: 3 | B31: Millwrighting | I31: =C31*E31*G31 | M31: =K31*I31 | O31: 0.85 | P31: =M31/O31
A32: 4 | B32: Temp Door | I32: =C32*E32*G32 | M32: =K32*I32 | O32: 0.85 | P32: =M32/O32
A33: 5 | B33: Bonding Costs | I33: =C33*E33*G33 | M33: =K33*I33 | O33: 0.85 | P33: =M33/O33
I34: =C34*E34*G34 | M34: =K34*I34 | O34: 0.85 | P34: =M34/O34
I35: =C35*E35*G35 | M35: =K35*I35 | O35: 0.85 | P35: =M35/O35
A36: Subtotal Subcontractors | P36: =SUM(P29:P35)
A37: Materials and Equipment
A38: Item | B38: Material Item | C38: Surcharge | E38: Units/Length | G38: Other | I38: Total Surcharge | K38: Unit Price | M38: Subtotal 1 | O38: Margin | P38: Subtotal 2
A39: 1 | B39: ABB SWGR | I39: =G39*E39*C39 | M39: =K39*I39 | O39: 0.85 | P39: =M39/O39
A40: 2 | B40: parking | I40: =G40*E40*C40 | M40: =K40*I40 | O40: 0.85 | P40: =M40/O40
A41: 3 | I41: =G41*E41*C41 | M41: =K41*I41 | O41: 0.85 | P41: =M41/O41
A42: 4 | I42: =G42*E42*C42 | M42: =K42*I42 | O42: 0.85 | P42: =M42/O42
A43: 5 | I43: =G43*E43*C43 | M43: =K43*I43 | O43: 0.85 | P43: =M43/O43
A44: 6 | I44: =G44*E44*C44 | M44: =K44*I44 | O44: 0.85 | P44: =M44/O44
A45: 7 | I45: =G45*E45*C45 | M45: =K45*I45 | O45: 0.85 | P45: =M45/O45
A46: 8 | I46: =G46*E46*C46 | M46: =K46*I46 | O46: 0.85 | P46: =M46/O46
A47: 9 | I47: =G47*E47*C47 | M47: =K47*I47 | O47: 0.85 | P47: =M47/O47
A48: 10 | I48: =G48*E48*C48 | M48: =K48*I48 | O48: 0.85 | P48: =M48/O48
A49: 11 | I49: =G49*E49*C49 | M49: =K49*I49 | O49: 0.85 | P49: =M49/O49
A50: 12 | I50: =G50*E50*C50 | M50: =K50*I50 | O50: 0.85 | P50: =M50/O50
A51: 13 | B51: Rigid 90deg - 2" | I51: =G51*E51*C51 | M51: =K51*I51 | O51: 0.85 | P51: =M51/O51
A52: 14 | B52: Rigid Bullet Hub Connectors - 2" and Nut | I52: =G52*E52*C52 | M52: =K52*I52 | O52: 0.85 | P52: =M52/O52
A53: 15 | B53: YGA282N - 2 Hole Lug, #4/o AWG | I53: =G53*E53*C53 | M53: =K53*I53 | O53: 0.85 | P53: =M53/O53
A54: 16 | B54: Mounting tape - VBH F-9473PB by 3M | I54: =G54*E54*C54 | M54: =K54*I54 | O54: 0.85 | P54: =M54/O54
A55: 17 | B55: Foam tape - VBH F-4910 by 3M | I55: =G55*E55*C55 | M55: =K55*I55 | O55: 0.85 | P55: =M55/O55
A56: 18 | B56: AS-7096N Sealant | I56: =G56*E56*C56 | M56: =K56*I56 | O56: 0.85 | P56: =M56/O56
A57: 19 | B57: Breaker HLL36060 | I57: =G57*E57*C57 | M57: =K57*I57 | O57: 0.85 | P57: =M57/O57
A58: 20 | B58: Pull Box, EEMAC-1 300mX300mmX150mm (P/N: CS12126) | I58: =G58*E58*C58 | M58: =K58*I58 | O58: 0.85 | P58: =M58/O58
A59: 27 | B59: Aluminum Bracket (Aluma Form) | I59: =G59*E59*C59 | M59: =K59*I59 | O59: 0.85 | P59: =M59/O59
A60: 28 | I60: =G60*E60*C60 | M60: =K60*I60 | O60: 0.85 | P60: =M60/O60
A61: 29 | I61: =G61*E61*C61 | M61: =K61*I61 | O61: 0.85 | P61: =M61/O61
A62: Subtotal Materials and Equipment | P62: =SUM(P39:P61)
A65: Project Subtotal | P65: =P26+P36+P62
A67: Cash Allowance | P67: 0
A69: Utility Isolation | P69: 0
A71: Discount | P71: 0
A73: Project Total | P73: =SUM(P65,P67,P69, P71)
A74: HST | P74: =P73*0.13
A75: TOTAL | P75: =P73+P74
A76: HST Check for final price should be the same as above | P76: =P73*1.13
B85: APS (Cost) | C85: Regular | D85: Regular W/truck | F85: Double Time | G85: Double Time W/truck | H85: Shift 20% | I85: Shift 20% W/truck
B86: FOREMAN | C86: 98.21 | D86: =(C86+17) | F86: 196.41 | G86: =(F86+17) | H86: 112.94 | I86: =H86+17
B87: JOURNEYMAN | C87: 87.65 | D87: =(C87+17) | F87: 175.31 | G87: =(F87+17) | H87: 100.8 | I87: =H87+17
B88: APPRENTICE #5 | C88: 71.38 | D88: =(C88+17) | F88: 142.73 | G88: =(F88+17) | H88: 82.09 | I88: =H88+17
B89: APPRENTICE #4 | C89: 63.34 | D89: =(C89+17) | F89: 126.7 | G89: =(F89+17) | H89: 72.84 | I89: =H89+17
B90: APPRENTICE #3 | C90: 55.33 | D90: =(C90+17) | F90: 110.64 | G90: =(F90+17) | H90: 63.63 | I90: =H90+17
B91: APPRENTICE #2 | C91: 47.3 | D91: =(C91+17) | F91: 94.59 | G91: =(F91+17) | H91: 54.4 | I91: =H91+17
B92: APPRENTICE #1 | C92: 39.25 | D92: =(C92+17) | F92: 78.49 | G92: =(F92+17) | H92: 45.14 | I92: =H92+17
B94: APS (Sell) | C94: Regular | D94: Regular W/truck | F94: Double Time | G94: Double Time W/truck | H94: Shift 20% | I94: Shift 20% W/truck | K94: Margin
B95: FOREMAN | C95: =C86/$K$95 | D95: =D86/$K$95 | F95: =F86/$K$95 | G95: =G86/$K$95 | H95: =H86/$K$95 | I95: =I86/$K$95 | K95: 0.8
B96: JOURNEYMAN | C96: =C87/$K$95 | D96: =D87/$K$95 | F96: =F87/$K$95 | G96: =G87/$K$95 | H96: =H87/$K$95 | I96: =I87/$K$95
B97: APPRENTICE #5 | C97: =C88/$K$95 | D97: =D88/$K$95 | F97: =F88/$K$95 | G97: =G88/$K$95 | H97: =H88/$K$95 | I97: =I88/$K$95
B98: APPRENTICE #4 | C98: =C89/$K$95 | D98: =D89/$K$95 | F98: =F89/$K$95 | G98: =G89/$K$95 | H98: =H89/$K$95 | I98: =I89/$K$95
B99: APPRENTICE #3 | C99: =C90/$K$95 | D99: =D90/$K$95 | F99: =F90/$K$95 | G99: =G90/$K$95 | H99: =H90/$K$95 | I99: =I90/$K$95
B100: APPRENTICE #2 | C100: =C91/$K$95 | D100: =D91/$K$95 | F100: =F91/$K$95 | G100: =G91/$K$95 | H100: =H91/$K$95 | I100: =I91/$K$95
B101: APPRENTICE #1 | C101: =C92/$K$95 | D101: =D92/$K$95 | F101: =F92/$K$95 | G101: =G92/$K$95 | H101: =H92/$K$95 | I101: =I92/$K$95
B104: Bonding | C104: rate/Moths
B105: First $2.5M | C105: 8.7 | G105: 2500000 | I105: =G105/1000*C105
B106: Second $2.5M | C106: 7.9 | G106: 2500000 | I106: =G106/1000*C106
B107: Third $2.5M | C107: 6.95 | G107: 2500000 | I107: =G107/1000*C107
B108: Subtotal | I108: =I105+I106+I107
B109: after 24 months | C109: 12 | I109: =I108*C109*0.01
B110: Grand Total for Bond | I110: =I108+I109
B111: Sell Price | I111: =I110/0.9

Sheet Location 5
A1: {=MID(CELL("filename",C1),FIND("]",CELL("filename",C1))+1,255)} | R1: {=MID(CELL("filename",C1),FIND("]",CELL("filename",C1))+1,255)}
A3: AINSWORTH LABOUR
A4: Item | B4: Task | C4: Regular Labour Rates | I4: Premium Labour Rates | O4: Margin | P4: Subtotal 3 - Sell Rate
C5: # of techs | D5: Days/Units | E5: Regular Hours | F5: Total Regular Hours | G5: Regular Labour Rate | H5: Subtotal 1 | I5: # of techs | J5: Days/Units | K5: O/T Hours | L5: Total O/T Hours | M5: O/T Labour Rate | N5: Subtotal 2
A6: Project Management | T6: =(P25+P36+P62)*0.05
A7: 1 | B7: Engineering/Meetings | C7: 0 | D7: 0 | F7: =C7*D7*E7 | G7: 90 | H7: =F7*G7 | L7: =I7*J7*K7 | M7: 150 | N7: =L7*M7 | O7: 0.85 | P7: =H7/O7+N7/O7
A8: 2 | B8: Project Management | C8: 0.05 | D8: 1 | E8: 1 | F8: =C8*D8*E8 | G8: =(P25+P36+P62) | H8: =F8*G8 | L8: =I8*J8*K8 | M8: 150 | N8: =L8*M8 | O8: 0.85 | P8: =H8/O8+N8/O8
A9: 3 | B9: ESA Submissions | F9: =C9*D9*E9 | G9: 2000 | H9: =F9*G9 | L9: =I9*J9*K9 | M9: 0 | N9: =L9*M9 | O9: 0.85 | P9: =H9/O9+N9/O9
A10: 4 | B10: Misc. Subcontractors | C10: 0.05 | D10: 1 | E10: 1 | F10: =C10*D10*E10 | G10: =P36 | H10: =F10*G10 | L10: =I10*J10*K10 | M10: 150 | N10: =L10*M10 | O10: 0.85 | P10: =H10/O10+N10/O10
A11: 5 | B11: Misc. Materials | C11: 0.05 | D11: 1 | E11: 1 | F11: =C11*D11*E11 | G11: =P62 | H11: =F11*G11 | L11: =I11*J11*K11 | M11: 150 | N11: =L11*M11 | O11: 0.85 | P11: =H11/O11+N11/O11
A12: 6 | B12: Forman - site supervision and civil | F12: =C12*D12*E12 | G12: 92 | H12: =F12*G12 | L12: =I12*J12*K12 | M12: 150 | N12: =L12*M12 | O12: 0.85 | P12: =H12/O12+N12/O12
A13: 7 | B13: Lodging | C13: 1 | D13: 1 | E13: 1 | F13: =C13*D13*E13 | G13: 0 | H13: =F13*G13 | L13: =I13*J13*K13 | M13: 175 | N13: =L13*M13 | O13: 0.85 | P13: =H13/O13+N13/O13
A14: Total Management | F14: =SUM(F7:F13) | H14: =SUM(H7:H13) | L14: =SUM(L7:L13) | N14: =SUM(N7:N13) | P14: =SUM(P7:P13)
A16: Labour
A17: 1 | B17: Mob/demob | F17: =C17*D17*E17 | G17: 108 | H17: =F17*G17 | L17: =I17*J17*K17 | M17: 195 | N17: =L17*M17 | O17: 0.85 | P17: =H17/O17+N17/O17
A18: 2 | B18: install | F18: =C18*D18*E18 | G18: 108 | H18: =F18*G18 | L18: =I18*J18*K18 | M18: 195 | N18: =L18*M18 | O18: 0.85 | P18: =H18/O18+N18/O18
A19: 3 | B19: assist | F19: =C19*D19*E19 | G19: 108 | H19: =F19*G19 | L19: =I19*J19*K19 | M19: 195 | N19: =L19*M19 | O19: 0.85 | P19: =H19/O19+N19/O19
A20: 4 | F20: =C20*D20*E20 | G20: 108 | H20: =F20*G20 | L20: =I20*J20*K20 | M20: 195 | N20: =L20*M20 | O20: 0.85 | P20: =H20/O20+N20/O20
A21: 5 | F21: =C21*D21*E21 | G21: 108 | H21: =F21*G21 | L21: =I21*J21*K21 | M21: 195 | N21: =L21*M21 | O21: 0.85 | P21: =H21/O21+N21/O21
A22: 6 | F22: =C22*D22*E22 | G22: 108 | H22: =F22*G22 | L22: =I22*J22*K22 | M22: 195 | N22: =L22*M22 | O22: 0.85 | P22: =H22/O22+N22/O22
A23: 7 | F23: =C23*D23*E23 | G23: 108 | H23: =F23*G23 | L23: =I23*J23*K23 | M23: 195 | N23: =L23*M23 | O23: 0.85 | P23: =H23/O23+N23/O23
A24: 8 | F24: =C24*D24*E24 | G24: 108 | H24: =F24*G24 | L24: =I24*J24*K24 | M24: 195 | N24: =L24*M24 | O24: 0.85 | P24: =H24/O24+N24/O24
A25: Sub Total Labour | F25: =SUM(F17:F24) | H25: =SUM(H17:H24) | L25: =SUM(L17:L24) | N25: =SUM(N17:N24) | P25: =SUM(P17:P24)
A26: Subtotal Labour | F26: =F14+F25 | H26: =H14+H25 | L26: =L14+L25 | N26: =N14+N25 | P26: =P14+P25
A27: Subcontractors
A28: Item | B28: Task | C28: Surcharge | E28: Days/Units | G28: Other | I28: Total Surcharge | K28: Unit Price | M28: Subtotal 1 | O28: Margin | P28: Subtotal 2
A29: 1 | B29: MG Power and Associates Inc | I29: =C29*E29*G29 | M29: =K29*I29 | O29: 0.85 | P29: =M29/O29
A30: 2 | B30: parking | I30: =C30*E30*G30 | M30: =K30*I30 | O30: 0.85 | P30: =M30/O30
A31: 3 | B31: Millwrighting | I31: =C31*E31*G31 | M31: =K31*I31 | O31: 0.85 | P31: =M31/O31
A32: 4 | B32: Temp Door | I32: =C32*E32*G32 | M32: =K32*I32 | O32: 0.85 | P32: =M32/O32
A33: 5 | B33: Bonding Costs | I33: =C33*E33*G33 | M33: =K33*I33 | O33: 0.85 | P33: =M33/O33
I34: =C34*E34*G34 | M34: =K34*I34 | O34: 0.85 | P34: =M34/O34
I35: =C35*E35*G35 | M35: =K35*I35 | O35: 0.85 | P35: =M35/O35
A36: Subtotal Subcontractors | P36: =SUM(P29:P35)
A37: Materials and Equipment
A38: Item | B38: Material Item | C38: Surcharge | E38: Units/Length | G38: Other | I38: Total Surcharge | K38: Unit Price | M38: Subtotal 1 | O38: Margin | P38: Subtotal 2
A39: 1 | B39: ABB SWGR | I39: =G39*E39*C39 | M39: =K39*I39 | O39: 0.85 | P39: =M39/O39
A40: 2 | B40: parking | I40: =G40*E40*C40 | M40: =K40*I40 | O40: 0.85 | P40: =M40/O40
A41: 3 | I41: =G41*E41*C41 | M41: =K41*I41 | O41: 0.85 | P41: =M41/O41
A42: 4 | I42: =G42*E42*C42 | M42: =K42*I42 | O42: 0.85 | P42: =M42/O42
A43: 5 | I43: =G43*E43*C43 | M43: =K43*I43 | O43: 0.85 | P43: =M43/O43
A44: 6 | I44: =G44*E44*C44 | M44: =K44*I44 | O44: 0.85 | P44: =M44/O44
A45: 7 | I45: =G45*E45*C45 | M45: =K45*I45 | O45: 0.85 | P45: =M45/O45
A46: 8 | I46: =G46*E46*C46 | M46: =K46*I46 | O46: 0.85 | P46: =M46/O46
A47: 9 | I47: =G47*E47*C47 | M47: =K47*I47 | O47: 0.85 | P47: =M47/O47
A48: 10 | I48: =G48*E48*C48 | M48: =K48*I48 | O48: 0.85 | P48: =M48/O48
A49: 11 | I49: =G49*E49*C49 | M49: =K49*I49 | O49: 0.85 | P49: =M49/O49
A50: 12 | I50: =G50*E50*C50 | M50: =K50*I50 | O50: 0.85 | P50: =M50/O50
A51: 13 | B51: Rigid 90deg - 2" | I51: =G51*E51*C51 | M51: =K51*I51 | O51: 0.85 | P51: =M51/O51
A52: 14 | B52: Rigid Bullet Hub Connectors - 2" and Nut | I52: =G52*E52*C52 | M52: =K52*I52 | O52: 0.85 | P52: =M52/O52
A53: 15 | B53: YGA282N - 2 Hole Lug, #4/o AWG | I53: =G53*E53*C53 | M53: =K53*I53 | O53: 0.85 | P53: =M53/O53
A54: 16 | B54: Mounting tape - VBH F-9473PB by 3M | I54: =G54*E54*C54 | M54: =K54*I54 | O54: 0.85 | P54: =M54/O54
A55: 17 | B55: Foam tape - VBH F-4910 by 3M | I55: =G55*E55*C55 | M55: =K55*I55 | O55: 0.85 | P55: =M55/O55
A56: 18 | B56: AS-7096N Sealant | I56: =G56*E56*C56 | M56: =K56*I56 | O56: 0.85 | P56: =M56/O56
A57: 19 | B57: Breaker HLL36060 | I57: =G57*E57*C57 | M57: =K57*I57 | O57: 0.85 | P57: =M57/O57
A58: 20 | B58: Pull Box, EEMAC-1 300mX300mmX150mm (P/N: CS12126) | I58: =G58*E58*C58 | M58: =K58*I58 | O58: 0.85 | P58: =M58/O58
A59: 27 | B59: Aluminum Bracket (Aluma Form) | I59: =G59*E59*C59 | M59: =K59*I59 | O59: 0.85 | P59: =M59/O59
A60: 28 | I60: =G60*E60*C60 | M60: =K60*I60 | O60: 0.85 | P60: =M60/O60
A61: 29 | I61: =G61*E61*C61 | M61: =K61*I61 | O61: 0.85 | P61: =M61/O61
A62: Subtotal Materials and Equipment | P62: =SUM(P39:P61)
A65: Project Subtotal | P65: =P26+P36+P62
A67: Cash Allowance | P67: 0
A69: Utility Isolation | P69: 0
A71: Discount | P71: 0
A73: Project Total | P73: =SUM(P65,P67,P69, P71)
A74: HST | P74: =P73*0.13
A75: TOTAL | P75: =P73+P74
A76: HST Check for final price should be the same as above | P76: =P73*1.13
B85: APS (Cost) | C85: Regular | D85: Regular W/truck | F85: Double Time | G85: Double Time W/truck | H85: Shift 20% | I85: Shift 20% W/truck
B86: FOREMAN | C86: 98.21 | D86: =(C86+17) | F86: 196.41 | G86: =(F86+17) | H86: 112.94 | I86: =H86+17
B87: JOURNEYMAN | C87: 87.65 | D87: =(C87+17) | F87: 175.31 | G87: =(F87+17) | H87: 100.8 | I87: =H87+17
B88: APPRENTICE #5 | C88: 71.38 | D88: =(C88+17) | F88: 142.73 | G88: =(F88+17) | H88: 82.09 | I88: =H88+17
B89: APPRENTICE #4 | C89: 63.34 | D89: =(C89+17) | F89: 126.7 | G89: =(F89+17) | H89: 72.84 | I89: =H89+17
B90: APPRENTICE #3 | C90: 55.33 | D90: =(C90+17) | F90: 110.64 | G90: =(F90+17) | H90: 63.63 | I90: =H90+17
B91: APPRENTICE #2 | C91: 47.3 | D91: =(C91+17) | F91: 94.59 | G91: =(F91+17) | H91: 54.4 | I91: =H91+17
B92: APPRENTICE #1 | C92: 39.25 | D92: =(C92+17) | F92: 78.49 | G92: =(F92+17) | H92: 45.14 | I92: =H92+17
B94: APS (Sell) | C94: Regular | D94: Regular W/truck | F94: Double Time | G94: Double Time W/truck | H94: Shift 20% | I94: Shift 20% W/truck | K94: Margin
B95: FOREMAN | C95: =C86/$K$95 | D95: =D86/$K$95 | F95: =F86/$K$95 | G95: =G86/$K$95 | H95: =H86/$K$95 | I95: =I86/$K$95 | K95: 0.8
B96: JOURNEYMAN | C96: =C87/$K$95 | D96: =D87/$K$95 | F96: =F87/$K$95 | G96: =G87/$K$95 | H96: =H87/$K$95 | I96: =I87/$K$95
B97: APPRENTICE #5 | C97: =C88/$K$95 | D97: =D88/$K$95 | F97: =F88/$K$95 | G97: =G88/$K$95 | H97: =H88/$K$95 | I97: =I88/$K$95
B98: APPRENTICE #4 | C98: =C89/$K$95 | D98: =D89/$K$95 | F98: =F89/$K$95 | G98: =G89/$K$95 | H98: =H89/$K$95 | I98: =I89/$K$95
B99: APPRENTICE #3 | C99: =C90/$K$95 | D99: =D90/$K$95 | F99: =F90/$K$95 | G99: =G90/$K$95 | H99: =H90/$K$95 | I99: =I90/$K$95
B100: APPRENTICE #2 | C100: =C91/$K$95 | D100: =D91/$K$95 | F100: =F91/$K$95 | G100: =G91/$K$95 | H100: =H91/$K$95 | I100: =I91/$K$95
B101: APPRENTICE #1 | C101: =C92/$K$95 | D101: =D92/$K$95 | F101: =F92/$K$95 | G101: =G92/$K$95 | H101: =H92/$K$95 | I101: =I92/$K$95
B104: Bonding | C104: rate/Moths
B105: First $2.5M | C105: 8.7 | G105: 2500000 | I105: =G105/1000*C105
B106: Second $2.5M | C106: 7.9 | G106: 2500000 | I106: =G106/1000*C106
B107: Third $2.5M | C107: 6.95 | G107: 2500000 | I107: =G107/1000*C107
B108: Subtotal | I108: =I105+I106+I107
B109: after 24 months | C109: 12 | I109: =I108*C109*0.01
B110: Grand Total for Bond | I110: =I108+I109
B111: Sell Price | I111: =I110/0.9

Sheet Location 6
A1: {=MID(CELL("filename",C1),FIND("]",CELL("filename",C1))+1,255)} | R1: {=MID(CELL("filename",C1),FIND("]",CELL("filename",C1))+1,255)}
A3: AINSWORTH LABOUR
A4: Item | B4: Task | C4: Regular Labour Rates | I4: Premium Labour Rates | O4: Margin | P4: Subtotal 3 - Sell Rate
C5: # of techs | D5: Days/Units | E5: Regular Hours | F5: Total Regular Hours | G5: Regular Labour Rate | H5: Subtotal 1 | I5: # of techs | J5: Days/Units | K5: O/T Hours | L5: Total O/T Hours | M5: O/T Labour Rate | N5: Subtotal 2
A6: Project Management | T6: =(P25+P36+P62)*0.05
A7: 1 | B7: Engineering/Meetings | C7: 0 | D7: 0 | F7: =C7*D7*E7 | G7: 90 | H7: =F7*G7 | L7: =I7*J7*K7 | M7: 150 | N7: =L7*M7 | O7: 0.85 | P7: =H7/O7+N7/O7
A8: 2 | B8: Project Management | C8: 0.05 | D8: 1 | E8: 1 | F8: =C8*D8*E8 | G8: =(P25+P36+P62) | H8: =F8*G8 | L8: =I8*J8*K8 | M8: 150 | N8: =L8*M8 | O8: 0.85 | P8: =H8/O8+N8/O8
A9: 3 | B9: ESA Submissions | F9: =C9*D9*E9 | G9: 2000 | H9: =F9*G9 | L9: =I9*J9*K9 | M9: 0 | N9: =L9*M9 | O9: 0.85 | P9: =H9/O9+N9/O9
A10: 4 | B10: Misc. Subcontractors | C10: 0.05 | D10: 1 | E10: 1 | F10: =C10*D10*E10 | G10: =P36 | H10: =F10*G10 | L10: =I10*J10*K10 | M10: 150 | N10: =L10*M10 | O10: 0.85 | P10: =H10/O10+N10/O10
A11: 5 | B11: Misc. Materials | C11: 0.05 | D11: 1 | E11: 1 | F11: =C11*D11*E11 | G11: =P62 | H11: =F11*G11 | L11: =I11*J11*K11 | M11: 150 | N11: =L11*M11 | O11: 0.85 | P11: =H11/O11+N11/O11
A12: 6 | B12: Forman - site supervision and civil | F12: =C12*D12*E12 | G12: 92 | H12: =F12*G12 | L12: =I12*J12*K12 | M12: 150 | N12: =L12*M12 | O12: 0.85 | P12: =H12/O12+N12/O12
A13: 7 | B13: Lodging | C13: 1 | D13: 1 | E13: 1 | F13: =C13*D13*E13 | G13: 0 | H13: =F13*G13 | L13: =I13*J13*K13 | M13: 175 | N13: =L13*M13 | O13: 0.85 | P13: =H13/O13+N13/O13
A14: Total Management | F14: =SUM(F7:F13) | H14: =SUM(H7:H13) | L14: =SUM(L7:L13) | N14: =SUM(N7:N13) | P14: =SUM(P7:P13)
A16: Labour
A17: 1 | B17: Mob/demob | F17: =C17*D17*E17 | G17: 108 | H17: =F17*G17 | L17: =I17*J17*K17 | M17: 195 | N17: =L17*M17 | O17: 0.85 | P17: =H17/O17+N17/O17
A18: 2 | B18: install | F18: =C18*D18*E18 | G18: 108 | H18: =F18*G18 | L18: =I18*J18*K18 | M18: 195 | N18: =L18*M18 | O18: 0.85 | P18: =H18/O18+N18/O18
A19: 3 | B19: assist | F19: =C19*D19*E19 | G19: 108 | H19: =F19*G19 | L19: =I19*J19*K19 | M19: 195 | N19: =L19*M19 | O19: 0.85 | P19: =H19/O19+N19/O19
A20: 4 | F20: =C20*D20*E20 | G20: 108 | H20: =F20*G20 | L20: =I20*J20*K20 | M20: 195 | N20: =L20*M20 | O20: 0.85 | P20: =H20/O20+N20/O20
A21: 5 | F21: =C21*D21*E21 | G21: 108 | H21: =F21*G21 | L21: =I21*J21*K21 | M21: 195 | N21: =L21*M21 | O21: 0.85 | P21: =H21/O21+N21/O21
A22: 6 | F22: =C22*D22*E22 | G22: 108 | H22: =F22*G22 | L22: =I22*J22*K22 | M22: 195 | N22: =L22*M22 | O22: 0.85 | P22: =H22/O22+N22/O22
A23: 7 | F23: =C23*D23*E23 | G23: 108 | H23: =F23*G23 | L23: =I23*J23*K23 | M23: 195 | N23: =L23*M23 | O23: 0.85 | P23: =H23/O23+N23/O23
A24: 8 | F24: =C24*D24*E24 | G24: 108 | H24: =F24*G24 | L24: =I24*J24*K24 | M24: 195 | N24: =L24*M24 | O24: 0.85 | P24: =H24/O24+N24/O24
A25: Sub Total Labour | F25: =SUM(F17:F24) | H25: =SUM(H17:H24) | L25: =SUM(L17:L24) | N25: =SUM(N17:N24) | P25: =SUM(P17:P24)
A26: Subtotal Labour | F26: =F14+F25 | H26: =H14+H25 | L26: =L14+L25 | N26: =N14+N25 | P26: =P14+P25
A27: Subcontractors
A28: Item | B28: Task | C28: Surcharge | E28: Days/Units | G28: Other | I28: Total Surcharge | K28: Unit Price | M28: Subtotal 1 | O28: Margin | P28: Subtotal 2
A29: 1 | B29: MG Power and Associates Inc | I29: =C29*E29*G29 | M29: =K29*I29 | O29: 0.85 | P29: =M29/O29
A30: 2 | B30: parking | I30: =C30*E30*G30 | M30: =K30*I30 | O30: 0.85 | P30: =M30/O30
A31: 3 | B31: Millwrighting | I31: =C31*E31*G31 | M31: =K31*I31 | O31: 0.85 | P31: =M31/O31
A32: 4 | B32: Temp Door | I32: =C32*E32*G32 | M32: =K32*I32 | O32: 0.85 | P32: =M32/O32
A33: 5 | B33: Bonding Costs | I33: =C33*E33*G33 | M33: =K33*I33 | O33: 0.85 | P33: =M33/O33
I34: =C34*E34*G34 | M34: =K34*I34 | O34: 0.85 | P34: =M34/O34
I35: =C35*E35*G35 | M35: =K35*I35 | O35: 0.85 | P35: =M35/O35
A36: Subtotal Subcontractors | P36: =SUM(P29:P35)
A37: Materials and Equipment
A38: Item | B38: Material Item | C38: Surcharge | E38: Units/Length | G38: Other | I38: Total Surcharge | K38: Unit Price | M38: Subtotal 1 | O38: Margin | P38: Subtotal 2
A39: 1 | B39: ABB SWGR | I39: =G39*E39*C39 | M39: =K39*I39 | O39: 0.85 | P39: =M39/O39
A40: 2 | B40: parking | I40: =G40*E40*C40 | M40: =K40*I40 | O40: 0.85 | P40: =M40/O40
A41: 3 | I41: =G41*E41*C41 | M41: =K41*I41 | O41: 0.85 | P41: =M41/O41
A42: 4 | I42: =G42*E42*C42 | M42: =K42*I42 | O42: 0.85 | P42: =M42/O42
A43: 5 | I43: =G43*E43*C43 | M43: =K43*I43 | O43: 0.85 | P43: =M43/O43
A44: 6 | I44: =G44*E44*C44 | M44: =K44*I44 | O44: 0.85 | P44: =M44/O44
A45: 7 | I45: =G45*E45*C45 | M45: =K45*I45 | O45: 0.85 | P45: =M45/O45
A46: 8 | I46: =G46*E46*C46 | M46: =K46*I46 | O46: 0.85 | P46: =M46/O46
A47: 9 | I47: =G47*E47*C47 | M47: =K47*I47 | O47: 0.85 | P47: =M47/O47
A48: 10 | I48: =G48*E48*C48 | M48: =K48*I48 | O48: 0.85 | P48: =M48/O48
A49: 11 | I49: =G49*E49*C49 | M49: =K49*I49 | O49: 0.85 | P49: =M49/O49
A50: 12 | I50: =G50*E50*C50 | M50: =K50*I50 | O50: 0.85 | P50: =M50/O50
A51: 13 | B51: Rigid 90deg - 2" | I51: =G51*E51*C51 | M51: =K51*I51 | O51: 0.85 | P51: =M51/O51
A52: 14 | B52: Rigid Bullet Hub Connectors - 2" and Nut | I52: =G52*E52*C52 | M52: =K52*I52 | O52: 0.85 | P52: =M52/O52
A53: 15 | B53: YGA282N - 2 Hole Lug, #4/o AWG | I53: =G53*E53*C53 | M53: =K53*I53 | O53: 0.85 | P53: =M53/O53
A54: 16 | B54: Mounting tape - VBH F-9473PB by 3M | I54: =G54*E54*C54 | M54: =K54*I54 | O54: 0.85 | P54: =M54/O54
A55: 17 | B55: Foam tape - VBH F-4910 by 3M | I55: =G55*E55*C55 | M55: =K55*I55 | O55: 0.85 | P55: =M55/O55
A56: 18 | B56: AS-7096N Sealant | I56: =G56*E56*C56 | M56: =K56*I56 | O56: 0.85 | P56: =M56/O56
A57: 19 | B57: Breaker HLL36060 | I57: =G57*E57*C57 | M57: =K57*I57 | O57: 0.85 | P57: =M57/O57
A58: 20 | B58: Pull Box, EEMAC-1 300mX300mmX150mm (P/N: CS12126) | I58: =G58*E58*C58 | M58: =K58*I58 | O58: 0.85 | P58: =M58/O58
A59: 27 | B59: Aluminum Bracket (Aluma Form) | I59: =G59*E59*C59 | M59: =K59*I59 | O59: 0.85 | P59: =M59/O59
A60: 28 | I60: =G60*E60*C60 | M60: =K60*I60 | O60: 0.85 | P60: =M60/O60
A61: 29 | I61: =G61*E61*C61 | M61: =K61*I61 | O61: 0.85 | P61: =M61/O61
A62: Subtotal Materials and Equipment | P62: =SUM(P39:P61)
A65: Project Subtotal | P65: =P26+P36+P62
A67: Cash Allowance | P67: 0
A69: Utility Isolation | P69: 0
A71: Discount | P71: 0
A73: Project Total | P73: =SUM(P65,P67,P69, P71)
A74: HST | P74: =P73*0.13
A75: TOTAL | P75: =P73+P74
A76: HST Check for final price should be the same as above | P76: =P73*1.13
B85: APS (Cost) | C85: Regular | D85: Regular W/truck | F85: Double Time | G85: Double Time W/truck | H85: Shift 20% | I85: Shift 20% W/truck
B86: FOREMAN | C86: 98.21 | D86: =(C86+17) | F86: 196.41 | G86: =(F86+17) | H86: 112.94 | I86: =H86+17
B87: JOURNEYMAN | C87: 87.65 | D87: =(C87+17) | F87: 175.31 | G87: =(F87+17) | H87: 100.8 | I87: =H87+17
B88: APPRENTICE #5 | C88: 71.38 | D88: =(C88+17) | F88: 142.73 | G88: =(F88+17) | H88: 82.09 | I88: =H88+17
B89: APPRENTICE #4 | C89: 63.34 | D89: =(C89+17) | F89: 126.7 | G89: =(F89+17) | H89: 72.84 | I89: =H89+17
B90: APPRENTICE #3 | C90: 55.33 | D90: =(C90+17) | F90: 110.64 | G90: =(F90+17) | H90: 63.63 | I90: =H90+17
B91: APPRENTICE #2 | C91: 47.3 | D91: =(C91+17) | F91: 94.59 | G91: =(F91+17) | H91: 54.4 | I91: =H91+17
B92: APPRENTICE #1 | C92: 39.25 | D92: =(C92+17) | F92: 78.49 | G92: =(F92+17) | H92: 45.14 | I92: =H92+17
B94: APS (Sell) | C94: Regular | D94: Regular W/truck | F94: Double Time | G94: Double Time W/truck | H94: Shift 20% | I94: Shift 20% W/truck | K94: Margin
B95: FOREMAN | C95: =C86/$K$95 | D95: =D86/$K$95 | F95: =F86/$K$95 | G95: =G86/$K$95 | H95: =H86/$K$95 | I95: =I86/$K$95 | K95: 0.8
B96: JOURNEYMAN | C96: =C87/$K$95 | D96: =D87/$K$95 | F96: =F87/$K$95 | G96: =G87/$K$95 | H96: =H87/$K$95 | I96: =I87/$K$95
B97: APPRENTICE #5 | C97: =C88/$K$95 | D97: =D88/$K$95 | F97: =F88/$K$95 | G97: =G88/$K$95 | H97: =H88/$K$95 | I97: =I88/$K$95
B98: APPRENTICE #4 | C98: =C89/$K$95 | D98: =D89/$K$95 | F98: =F89/$K$95 | G98: =G89/$K$95 | H98: =H89/$K$95 | I98: =I89/$K$95
B99: APPRENTICE #3 | C99: =C90/$K$95 | D99: =D90/$K$95 | F99: =F90/$K$95 | G99: =G90/$K$95 | H99: =H90/$K$95 | I99: =I90/$K$95
B100: APPRENTICE #2 | C100: =C91/$K$95 | D100: =D91/$K$95 | F100: =F91/$K$95 | G100: =G91/$K$95 | H100: =H91/$K$95 | I100: =I91/$K$95
B101: APPRENTICE #1 | C101: =C92/$K$95 | D101: =D92/$K$95 | F101: =F92/$K$95 | G101: =G92/$K$95 | H101: =H92/$K$95 | I101: =I92/$K$95
B104: Bonding | C104: rate/Moths
B105: First $2.5M | C105: 8.7 | G105: 2500000 | I105: =G105/1000*C105
B106: Second $2.5M | C106: 7.9 | G106: 2500000 | I106: =G106/1000*C106
B107: Third $2.5M | C107: 6.95 | G107: 2500000 | I107: =G107/1000*C107
B108: Subtotal | I108: =I105+I106+I107
B109: after 24 months | C109: 12 | I109: =I108*C109*0.01
B110: Grand Total for Bond | I110: =I108+I109
B111: Sell Price | I111: =I110/0.9

Sheet Option 1
A1: {=MID(CELL("filename",C1),FIND("]",CELL("filename",C1))+1,255)} | R1: {=MID(CELL("filename",C1),FIND("]",CELL("filename",C1))+1,255)}
A3: AINSWORTH LABOUR
A4: Item | B4: Task | C4: Regular Labour Rates | I4: Premium Labour Rates | O4: Margin | P4: Subtotal 3 - Sell Rate
C5: # of techs | D5: Days/Units | E5: Regular Hours | F5: Total Regular Hours | G5: Regular Labour Rate | H5: Subtotal 1 | I5: # of techs | J5: Days/Units | K5: O/T Hours | L5: Total O/T Hours | M5: O/T Labour Rate | N5: Subtotal 2
A6: Project Management | T6: =(P25+P36+P62)*0.05
A7: 1 | B7: Engineering/Meetings | C7: 0 | D7: 0 | F7: =C7*D7*E7 | G7: 90 | H7: =F7*G7 | L7: =I7*J7*K7 | M7: 150 | N7: =L7*M7 | O7: 0.85 | P7: =H7/O7+N7/O7
A8: 2 | B8: Project Management | C8: 0.05 | D8: 1 | E8: 1 | F8: =C8*D8*E8 | G8: =(P25+P36+P62) | H8: =F8*G8 | L8: =I8*J8*K8 | M8: 150 | N8: =L8*M8 | O8: 0.85 | P8: =H8/O8+N8/O8
A9: 3 | B9: ESA Submissions | F9: =C9*D9*E9 | G9: 2000 | H9: =F9*G9 | L9: =I9*J9*K9 | M9: 0 | N9: =L9*M9 | O9: 0.85 | P9: =H9/O9+N9/O9
A10: 4 | B10: Misc. Subcontractors | C10: 0.05 | D10: 1 | E10: 1 | F10: =C10*D10*E10 | G10: =P36 | H10: =F10*G10 | L10: =I10*J10*K10 | M10: 150 | N10: =L10*M10 | O10: 0.85 | P10: =H10/O10+N10/O10
A11: 5 | B11: Misc. Materials | C11: 0.05 | D11: 1 | E11: 1 | F11: =C11*D11*E11 | G11: =P62 | H11: =F11*G11 | L11: =I11*J11*K11 | M11: 150 | N11: =L11*M11 | O11: 0.85 | P11: =H11/O11+N11/O11
A12: 6 | B12: Forman - site supervision and civil | F12: =C12*D12*E12 | G12: 92 | H12: =F12*G12 | L12: =I12*J12*K12 | M12: 150 | N12: =L12*M12 | O12: 0.85 | P12: =H12/O12+N12/O12
A13: 7 | B13: Lodging | C13: 1 | D13: 1 | E13: 1 | F13: =C13*D13*E13 | G13: 0 | H13: =F13*G13 | L13: =I13*J13*K13 | M13: 175 | N13: =L13*M13 | O13: 0.85 | P13: =H13/O13+N13/O13
A14: Total Management | F14: =SUM(F7:F13) | H14: =SUM(H7:H13) | L14: =SUM(L7:L13) | N14: =SUM(N7:N13) | P14: =SUM(P7:P13)
A16: Labour
A17: 1 | B17: Mob/demob | F17: =C17*D17*E17 | G17: 108 | H17: =F17*G17 | L17: =I17*J17*K17 | M17: 195 | N17: =L17*M17 | O17: 0.85 | P17: =H17/O17+N17/O17
A18: 2 | B18: install | F18: =C18*D18*E18 | G18: 108 | H18: =F18*G18 | L18: =I18*J18*K18 | M18: 195 | N18: =L18*M18 | O18: 0.85 | P18: =H18/O18+N18/O18
A19: 3 | B19: assist | F19: =C19*D19*E19 | G19: 108 | H19: =F19*G19 | L19: =I19*J19*K19 | M19: 195 | N19: =L19*M19 | O19: 0.85 | P19: =H19/O19+N19/O19
A20: 4 | F20: =C20*D20*E20 | G20: 108 | H20: =F20*G20 | L20: =I20*J20*K20 | M20: 195 | N20: =L20*M20 | O20: 0.85 | P20: =H20/O20+N20/O20
A21: 5 | F21: =C21*D21*E21 | G21: 108 | H21: =F21*G21 | L21: =I21*J21*K21 | M21: 195 | N21: =L21*M21 | O21: 0.85 | P21: =H21/O21+N21/O21
A22: 6 | F22: =C22*D22*E22 | G22: 108 | H22: =F22*G22 | L22: =I22*J22*K22 | M22: 195 | N22: =L22*M22 | O22: 0.85 | P22: =H22/O22+N22/O22
A23: 7 | F23: =C23*D23*E23 | G23: 108 | H23: =F23*G23 | L23: =I23*J23*K23 | M23: 195 | N23: =L23*M23 | O23: 0.85 | P23: =H23/O23+N23/O23
A24: 8 | F24: =C24*D24*E24 | G24: 108 | H24: =F24*G24 | L24: =I24*J24*K24 | M24: 195 | N24: =L24*M24 | O24: 0.85 | P24: =H24/O24+N24/O24
A25: Sub Total Labour | F25: =SUM(F17:F24) | H25: =SUM(H17:H24) | L25: =SUM(L17:L24) | N25: =SUM(N17:N24) | P25: =SUM(P17:P24)
A26: Subtotal Labour | F26: =F14+F25 | H26: =H14+H25 | L26: =L14+L25 | N26: =N14+N25 | P26: =P14+P25
A27: Subcontractors
A28: Item | B28: Task | C28: Surcharge | E28: Days/Units | G28: Other | I28: Total Surcharge | K28: Unit Price | M28: Subtotal 1 | O28: Margin | P28: Subtotal 2
A29: 1 | B29: MG Power and Associates Inc | I29: =C29*E29*G29 | M29: =K29*I29 | O29: 0.85 | P29: =M29/O29
A30: 2 | B30: parking | I30: =C30*E30*G30 | M30: =K30*I30 | O30: 0.85 | P30: =M30/O30
A31: 3 | B31: Millwrighting | I31: =C31*E31*G31 | M31: =K31*I31 | O31: 0.85 | P31: =M31/O31
A32: 4 | B32: Temp Door | I32: =C32*E32*G32 | M32: =K32*I32 | O32: 0.85 | P32: =M32/O32
A33: 5 | B33: Bonding Costs | I33: =C33*E33*G33 | M33: =K33*I33 | O33: 0.85 | P33: =M33/O33
I34: =C34*E34*G34 | M34: =K34*I34 | O34: 0.85 | P34: =M34/O34
I35: =C35*E35*G35 | M35: =K35*I35 | O35: 0.85 | P35: =M35/O35
A36: Subtotal Subcontractors | P36: =SUM(P29:P35)
A37: Materials and Equipment
A38: Item | B38: Material Item | C38: Surcharge | E38: Units/Length | G38: Other | I38: Total Surcharge | K38: Unit Price | M38: Subtotal 1 | O38: Margin | P38: Subtotal 2
A39: 1 | B39: ABB SWGR | I39: =G39*E39*C39 | M39: =K39*I39 | O39: 0.85 | P39: =M39/O39
A40: 2 | B40: parking | I40: =G40*E40*C40 | M40: =K40*I40 | O40: 0.85 | P40: =M40/O40
A41: 3 | I41: =G41*E41*C41 | M41: =K41*I41 | O41: 0.85 | P41: =M41/O41
A42: 4 | I42: =G42*E42*C42 | M42: =K42*I42 | O42: 0.85 | P42: =M42/O42
A43: 5 | I43: =G43*E43*C43 | M43: =K43*I43 | O43: 0.85 | P43: =M43/O43
A44: 6 | I44: =G44*E44*C44 | M44: =K44*I44 | O44: 0.85 | P44: =M44/O44
A45: 7 | I45: =G45*E45*C45 | M45: =K45*I45 | O45: 0.85 | P45: =M45/O45
A46: 8 | I46: =G46*E46*C46 | M46: =K46*I46 | O46: 0.85 | P46: =M46/O46
A47: 9 | I47: =G47*E47*C47 | M47: =K47*I47 | O47: 0.85 | P47: =M47/O47
A48: 10 | I48: =G48*E48*C48 | M48: =K48*I48 | O48: 0.85 | P48: =M48/O48
A49: 11 | I49: =G49*E49*C49 | M49: =K49*I49 | O49: 0.85 | P49: =M49/O49
A50: 12 | I50: =G50*E50*C50 | M50: =K50*I50 | O50: 0.85 | P50: =M50/O50
A51: 13 | B51: Rigid 90deg - 2" | I51: =G51*E51*C51 | M51: =K51*I51 | O51: 0.85 | P51: =M51/O51
A52: 14 | B52: Rigid Bullet Hub Connectors - 2" and Nut | I52: =G52*E52*C52 | M52: =K52*I52 | O52: 0.85 | P52: =M52/O52
A53: 15 | B53: YGA282N - 2 Hole Lug, #4/o AWG | I53: =G53*E53*C53 | M53: =K53*I53 | O53: 0.85 | P53: =M53/O53
A54: 16 | B54: Mounting tape - VBH F-9473PB by 3M | I54: =G54*E54*C54 | M54: =K54*I54 | O54: 0.85 | P54: =M54/O54
A55: 17 | B55: Foam tape - VBH F-4910 by 3M | I55: =G55*E55*C55 | M55: =K55*I55 | O55: 0.85 | P55: =M55/O55
A56: 18 | B56: AS-7096N Sealant | I56: =G56*E56*C56 | M56: =K56*I56 | O56: 0.85 | P56: =M56/O56
A57: 19 | B57: Breaker HLL36060 | I57: =G57*E57*C57 | M57: =K57*I57 | O57: 0.85 | P57: =M57/O57
A58: 20 | B58: Pull Box, EEMAC-1 300mX300mmX150mm (P/N: CS12126) | I58: =G58*E58*C58 | M58: =K58*I58 | O58: 0.85 | P58: =M58/O58
A59: 27 | B59: Aluminum Bracket (Aluma Form) | I59: =G59*E59*C59 | M59: =K59*I59 | O59: 0.85 | P59: =M59/O59
A60: 28 | I60: =G60*E60*C60 | M60: =K60*I60 | O60: 0.85 | P60: =M60/O60
A61: 29 | I61: =G61*E61*C61 | M61: =K61*I61 | O61: 0.85 | P61: =M61/O61
A62: Subtotal Materials and Equipment | P62: =SUM(P39:P61)
A65: Project Subtotal | P65: =P26+P36+P62
A67: Cash Allowance | P67: 0
A69: Utility Isolation | P69: 0
A71: Discount | P71: 0
A73: Project Total | P73: =SUM(P65,P67,P69, P71)
A74: HST | P74: =P73*0.13
A75: TOTAL | P75: =P73+P74
A76: HST Check for final price should be the same as above | P76: =P73*1.13
B85: APS (Cost) | C85: Regular | D85: Regular W/truck | F85: Double Time | G85: Double Time W/truck | H85: Shift 20% | I85: Shift 20% W/truck
B86: FOREMAN | C86: 98.21 | D86: =(C86+17) | F86: 196.41 | G86: =(F86+17) | H86: 112.94 | I86: =H86+17
B87: JOURNEYMAN | C87: 87.65 | D87: =(C87+17) | F87: 175.31 | G87: =(F87+17) | H87: 100.8 | I87: =H87+17
B88: APPRENTICE #5 | C88: 71.38 | D88: =(C88+17) | F88: 142.73 | G88: =(F88+17) | H88: 82.09 | I88: =H88+17
B89: APPRENTICE #4 | C89: 63.34 | D89: =(C89+17) | F89: 126.7 | G89: =(F89+17) | H89: 72.84 | I89: =H89+17
B90: APPRENTICE #3 | C90: 55.33 | D90: =(C90+17) | F90: 110.64 | G90: =(F90+17) | H90: 63.63 | I90: =H90+17
B91: APPRENTICE #2 | C91: 47.3 | D91: =(C91+17) | F91: 94.59 | G91: =(F91+17) | H91: 54.4 | I91: =H91+17
B92: APPRENTICE #1 | C92: 39.25 | D92: =(C92+17) | F92: 78.49 | G92: =(F92+17) | H92: 45.14 | I92: =H92+17
B94: APS (Sell) | C94: Regular | D94: Regular W/truck | F94: Double Time | G94: Double Time W/truck | H94: Shift 20% | I94: Shift 20% W/truck | K94: Margin
B95: FOREMAN | C95: =C86/$K$95 | D95: =D86/$K$95 | F95: =F86/$K$95 | G95: =G86/$K$95 | H95: =H86/$K$95 | I95: =I86/$K$95 | K95: 0.8
B96: JOURNEYMAN | C96: =C87/$K$95 | D96: =D87/$K$95 | F96: =F87/$K$95 | G96: =G87/$K$95 | H96: =H87/$K$95 | I96: =I87/$K$95
B97: APPRENTICE #5 | C97: =C88/$K$95 | D97: =D88/$K$95 | F97: =F88/$K$95 | G97: =G88/$K$95 | H97: =H88/$K$95 | I97: =I88/$K$95
B98: APPRENTICE #4 | C98: =C89/$K$95 | D98: =D89/$K$95 | F98: =F89/$K$95 | G98: =G89/$K$95 | H98: =H89/$K$95 | I98: =I89/$K$95
B99: APPRENTICE #3 | C99: =C90/$K$95 | D99: =D90/$K$95 | F99: =F90/$K$95 | G99: =G90/$K$95 | H99: =H90/$K$95 | I99: =I90/$K$95
B100: APPRENTICE #2 | C100: =C91/$K$95 | D100: =D91/$K$95 | F100: =F91/$K$95 | G100: =G91/$K$95 | H100: =H91/$K$95 | I100: =I91/$K$95
B101: APPRENTICE #1 | C101: =C92/$K$95 | D101: =D92/$K$95 | F101: =F92/$K$95 | G101: =G92/$K$95 | H101: =H92/$K$95 | I101: =I92/$K$95
B104: Bonding | C104: rate/Moths
B105: First $2.5M | C105: 8.7 | G105: 2500000 | I105: =G105/1000*C105
B106: Second $2.5M | C106: 7.9 | G106: 2500000 | I106: =G106/1000*C106
B107: Third $2.5M | C107: 6.95 | G107: 2500000 | I107: =G107/1000*C107
B108: Subtotal | I108: =I105+I106+I107
B109: after 24 months | C109: 12 | I109: =I108*C109*0.01
B110: Grand Total for Bond | I110: =I108+I109
B111: Sell Price | I111: =I110/0.9
